Workbook

Sheet Cover
B2: Engagement Plan
B3: Merchant Payment Operations & Dispute Hub
B5: Document | C5: Engagement overview, stakeholder engagement, RACI, governance, communications and deliverables
B6: Version | C6: 1.0
B7: Reporting date | C7: 46275
B8: Prepared by | C8: Bhawna, Product Owner
B9: Companion documents | C9: RAID_Log, Change_Log, Product_Backlog, RTM, KPI_Definitions and Business_Case_GTM workbooks
B10: Project type | C10: Simulation / portfolio project prepared to demonstrate Product Owner practice. Not an actual client engagement; stakeholders are roles, not real people, and all dates are illustrative.
B12: Purpose
B13: Sets out how the engagement is run and how stakeholders are brought along: what we are delivering and why, who needs to be involved and how, who decides what, which forums make decisions, how we communicate, and which deliverables are due. The Dashboard highlights engagement gaps, overdue actions, upcoming governance and RACI issues.
B15: Stakeholder engagement levels
B16: Level | C16: Meaning
B17: 1 · Unaware | C17: Doesn't yet know about the engagement or how it affects them.
B18: 2 · Resistant | C18: Aware and opposed, or pushing for a conflicting outcome.
B19: 3 · Neutral | C19: Aware but not actively supporting or opposing.
B20: 4 · Supportive | C20: Aware and supports the approach and decisions.
B21: 5 · Leading | C21: Actively champions the work and influences others.
B23: Influence and interest quadrants
B24: Quadrant | C24: Approach
B25: Manage closely | C25: High influence, high interest. Involve in decisions; engage frequently and personally.
B26: Keep satisfied | C26: High influence, lower interest. Brief on decisions that affect them; avoid overloading.
B27: Keep informed | C27: Lower influence, high interest. Share progress regularly and use their feedback.
B28: Monitor | C28: Lower influence and interest. Light-touch updates; watch for changes.
B29: The threshold for 'high' is set on the Stakeholder Register tab (default 4 on a 1–5 scale).
B31: RACI
B32: Code | C32: Meaning
B33: R · Responsible | C33: Does the work. At least one per activity.
B34: A · Accountable | C34: Owns the outcome and makes the final decision. Exactly one per activity.
B35: C · Consulted | C35: Gives input before the decision; two-way conversation.
B36: I · Informed | C36: Told about the outcome; one-way communication.
B37: R/A | C37: Responsible and accountable (does the work and owns the decision).
B39: How to maintain
B40: 1. Update current engagement, last contact and next action for each stakeholder after key interactions; review weekly with the Engagement Lead.
B41: 2. Re-score influence and interest at each phase change (for example before pilot and before each wave).
B42: 3. Keep RACI in step with the Change Log decision thresholds; the check column flags rows without exactly one A.
B43: 4. Update governance next dates and communication next send dates after each meeting or send.
B44: Grey columns calculate automatically. Dashboard date windows use the reporting date above.
B46: Version history
B47: Version | C47: Date | D47: Author | E47: Change summary
B48: 1.0 | C48: 46275 | D48: Bhawna | E48: Initial engagement plan: 18 stakeholders, 18 RACI activities, 13 governance forums, 12 communications, 16 deliverables.

Sheet Dashboard
B1: Engagement Dashboard
B2: Merchant Payment Operations & Dispute Hub · Simulation project · Figures update automatically
B3: ="Reporting date: "&TEXT(Cover!$C$7,"DD-MMM-YYYY") -> Reporting date: 10-Sep-2026
B5: Summary
B6: Stakeholders | C6: Manage closely | D6: With engagement gap | E6: Resistant or unaware | F6: Overdue stakeholder actions | G6: Governance meetings in next 14 days | H6: Deliverables in review | I6: RACI rows to fix
B7: =COUNTA('Stakeholder Register'!$A$5:$A$54) -> 18 | C7: =COUNTIFS('Stakeholder Register'!$G$5:$G$54,"Manage closely") -> 5 | D7: =COUNTIFS('Stakeholder Register'!$J$5:$J$54,">0") -> 14 | E7: =COUNTIFS('Stakeholder Register'!$H$5:$H$54,"Resistant")+COUNTIFS('Stakeholder Register'!$H$5:$H$54,"Unaware") -> 3 | F7: =COUNTIFS('Stakeholder Register'!$U$5:$U$54,"Overdue") -> 1 | G7: =COUNT(Governance!$K$5:$K$34) -> 10 | H7: =COUNTIFS(Deliverables!$H$5:$H$54,"In Review") -> 4 | I7: =COUNTIFS('RACI Matrix'!$T$5:$T$40,"Needs*") -> 0
B9: Influence and interest map
B10: Influence ↑ | C10: ="Keep satisfied ("&COUNTIFS('Stakeholder Register'!$G$5:$G$54,"Keep satisfied")&")" -> Keep satisfied (4) | F10: ="Manage closely ("&COUNTIFS('Stakeholder Register'!$G$5:$G$54,"Manage closely")&")" -> Manage closely (5)
B11: Higher | C11: =IFERROR(INDEX('Stakeholder Register'!$B$5:$B$54,MATCH(SMALL('Stakeholder Register'!$W$5:$W$54,1),'Stakeholder Register'!$W$5:$W$54,0)),"") -> Steering Committee (finance, technology and risk delegates) | F11: =IFERROR(INDEX('Stakeholder Register'!$B$5:$B$54,MATCH(SMALL('Stakeholder Register'!$V$5:$V$54,1),'Stakeholder Register'!$V$5:$V$54,0)),"") -> Business Sponsor (Head of Merchant Services)
C12: =IFERROR(INDEX('Stakeholder Register'!$B$5:$B$54,MATCH(SMALL('Stakeholder Register'!$W$5:$W$54,2),'Stakeholder Register'!$W$5:$W$54,0)),"") -> InfoSec Lead | F12: =IFERROR(INDEX('Stakeholder Register'!$B$5:$B$54,MATCH(SMALL('Stakeholder Register'!$V$5:$V$54,2),'Stakeholder Register'!$V$5:$V$54,0)),"") -> Dispute Ops Lead
C13: =IFERROR(INDEX('Stakeholder Register'!$B$5:$B$54,MATCH(SMALL('Stakeholder Register'!$W$5:$W$54,3),'Stakeholder Register'!$W$5:$W$54,0)),"") -> Data Governance Lead | F13: =IFERROR(INDEX('Stakeholder Register'!$B$5:$B$54,MATCH(SMALL('Stakeholder Register'!$V$5:$V$54,3),'Stakeholder Register'!$V$5:$V$54,0)),"") -> Finance Lead
C14: =IFERROR(INDEX('Stakeholder Register'!$B$5:$B$54,MATCH(SMALL('Stakeholder Register'!$W$5:$W$54,4),'Stakeholder Register'!$W$5:$W$54,0)),"") -> Payment Processor Account Manager | F14: =IFERROR(INDEX('Stakeholder Register'!$B$5:$B$54,MATCH(SMALL('Stakeholder Register'!$V$5:$V$54,4),'Stakeholder Register'!$V$5:$V$54,0)),"") -> Compliance Lead
C15: =IFERROR(INDEX('Stakeholder Register'!$B$5:$B$54,MATCH(SMALL('Stakeholder Register'!$W$5:$W$54,5),'Stakeholder Register'!$W$5:$W$54,0)),"") | F15: =IFERROR(INDEX('Stakeholder Register'!$B$5:$B$54,MATCH(SMALL('Stakeholder Register'!$V$5:$V$54,5),'Stakeholder Register'!$V$5:$V$54,0)),"") -> Merchant Relationship Lead
C16: =IFERROR(INDEX('Stakeholder Register'!$B$5:$B$54,MATCH(SMALL('Stakeholder Register'!$W$5:$W$54,6),'Stakeholder Register'!$W$5:$W$54,0)),"") | F16: =IFERROR(INDEX('Stakeholder Register'!$B$5:$B$54,MATCH(SMALL('Stakeholder Register'!$V$5:$V$54,6),'Stakeholder Register'!$V$5:$V$54,0)),"")
C17: =IFERROR(INDEX('Stakeholder Register'!$B$5:$B$54,MATCH(SMALL('Stakeholder Register'!$W$5:$W$54,7),'Stakeholder Register'!$W$5:$W$54,0)),"") | F17: =IFERROR(INDEX('Stakeholder Register'!$B$5:$B$54,MATCH(SMALL('Stakeholder Register'!$V$5:$V$54,7),'Stakeholder Register'!$V$5:$V$54,0)),"")
C18: =IFERROR(INDEX('Stakeholder Register'!$B$5:$B$54,MATCH(SMALL('Stakeholder Register'!$W$5:$W$54,8),'Stakeholder Register'!$W$5:$W$54,0)),"") | F18: =IFERROR(INDEX('Stakeholder Register'!$B$5:$B$54,MATCH(SMALL('Stakeholder Register'!$V$5:$V$54,8),'Stakeholder Register'!$V$5:$V$54,0)),"")
C20: ="Monitor ("&COUNTIFS('Stakeholder Register'!$G$5:$G$54,"Monitor")&")" -> Monitor (6) | F20: ="Keep informed ("&COUNTIFS('Stakeholder Register'!$G$5:$G$54,"Keep informed")&")" -> Keep informed (3)
B21: Lower | C21: =IFERROR(INDEX('Stakeholder Register'!$B$5:$B$54,MATCH(SMALL('Stakeholder Register'!$Y$5:$Y$54,1),'Stakeholder Register'!$Y$5:$Y$54,0)),"") -> Legal Counsel | F21: =IFERROR(INDEX('Stakeholder Register'!$B$5:$B$54,MATCH(SMALL('Stakeholder Register'!$X$5:$X$54,1),'Stakeholder Register'!$X$5:$X$54,0)),"") -> Fraud Operations Lead
C22: =IFERROR(INDEX('Stakeholder Register'!$B$5:$B$54,MATCH(SMALL('Stakeholder Register'!$Y$5:$Y$54,2),'Stakeholder Register'!$Y$5:$Y$54,0)),"") -> IAM Team Lead | F22: =IFERROR(INDEX('Stakeholder Register'!$B$5:$B$54,MATCH(SMALL('Stakeholder Register'!$X$5:$X$54,2),'Stakeholder Register'!$X$5:$X$54,0)),"") -> Pilot merchants (10)
C23: =IFERROR(INDEX('Stakeholder Register'!$B$5:$B$54,MATCH(SMALL('Stakeholder Register'!$Y$5:$Y$54,3),'Stakeholder Register'!$Y$5:$Y$54,0)),"") -> Data Engineering Lead | F23: =IFERROR(INDEX('Stakeholder Register'!$B$5:$B$54,MATCH(SMALL('Stakeholder Register'!$X$5:$X$54,3),'Stakeholder Register'!$X$5:$X$54,0)),"") -> Delivery squads (Portal, Integration, Data)
C24: =IFERROR(INDEX('Stakeholder Register'!$B$5:$B$54,MATCH(SMALL('Stakeholder Register'!$Y$5:$Y$54,4),'Stakeholder Register'!$Y$5:$Y$54,0)),"") -> Customer Servicing Lead | F24: =IFERROR(INDEX('Stakeholder Register'!$B$5:$B$54,MATCH(SMALL('Stakeholder Register'!$X$5:$X$54,4),'Stakeholder Register'!$X$5:$X$54,0)),"")
C25: =IFERROR(INDEX('Stakeholder Register'!$B$5:$B$54,MATCH(SMALL('Stakeholder Register'!$Y$5:$Y$54,5),'Stakeholder Register'!$Y$5:$Y$54,0)),"") -> Marketing and Merchant Communications Lead | F25: =IFERROR(INDEX('Stakeholder Register'!$B$5:$B$54,MATCH(SMALL('Stakeholder Register'!$X$5:$X$54,5),'Stakeholder Register'!$X$5:$X$54,0)),"")
C26: =IFERROR(INDEX('Stakeholder Register'!$B$5:$B$54,MATCH(SMALL('Stakeholder Register'!$Y$5:$Y$54,6),'Stakeholder Register'!$Y$5:$Y$54,0)),"") -> Document Storage Vendor | F26: =IFERROR(INDEX('Stakeholder Register'!$B$5:$B$54,MATCH(SMALL('Stakeholder Register'!$X$5:$X$54,6),'Stakeholder Register'!$X$5:$X$54,0)),"")
C27: =IFERROR(INDEX('Stakeholder Register'!$B$5:$B$54,MATCH(SMALL('Stakeholder Register'!$Y$5:$Y$54,7),'Stakeholder Register'!$Y$5:$Y$54,0)),"") | F27: =IFERROR(INDEX('Stakeholder Register'!$B$5:$B$54,MATCH(SMALL('Stakeholder Register'!$X$5:$X$54,7),'Stakeholder Register'!$X$5:$X$54,0)),"")
C28: =IFERROR(INDEX('Stakeholder Register'!$B$5:$B$54,MATCH(SMALL('Stakeholder Register'!$Y$5:$Y$54,8),'Stakeholder Register'!$Y$5:$Y$54,0)),"") | F28: =IFERROR(INDEX('Stakeholder Register'!$B$5:$B$54,MATCH(SMALL('Stakeholder Register'!$X$5:$X$54,8),'Stakeholder Register'!$X$5:$X$54,0)),"")
C29: Lower interest | F29: Interest → | G29: Higher interest
B31: Biggest engagement gaps (gap × influence)
B32: ID | C32: Stakeholder | D32: Current | E32: Desired | F32: Gap | G32: Next action | I32: Due
B33: =IFERROR(INDEX('Stakeholder Register'!$A$5:$A$54,MATCH(LARGE('Stakeholder Register'!$Z$5:$Z$54,1),'Stakeholder Register'!$Z$5:$Z$54,0)),"") -> SH-05 | C33: =IFERROR(INDEX('Stakeholder Register'!$B$5:$B$54,MATCH(LARGE('Stakeholder Register'!$Z$5:$Z$54,1),'Stakeholder Register'!$Z$5:$Z$54,0)),"") -> Fraud Operations Lead | D33: =IFERROR(INDEX('Stakeholder Register'!$H$5:$H$54,MATCH(LARGE('Stakeholder Register'!$Z$5:$Z$54,1),'Stakeholder Register'!$Z$5:$Z$54,0)),"") -> Resistant | E33: =IFERROR(INDEX('Stakeholder Register'!$I$5:$I$54,MATCH(LARGE('Stakeholder Register'!$Z$5:$Z$54,1),'Stakeholder Register'!$Z$5:$Z$54,0)),"") -> Supportive | F33: =IFERROR(INDEX('Stakeholder Register'!$J$5:$J$54,MATCH(LARGE('Stakeholder Register'!$Z$5:$Z$54,1),'Stakeholder Register'!$Z$5:$Z$54,0)),"") -> 2 | G33: =IFERROR(INDEX('Stakeholder Register'!$S$5:$S$54,MATCH(LARGE('Stakeholder Register'!$Z$5:$Z$54,1),'Stakeholder Register'!$Z$5:$Z$54,0)),"") -> Share CR-01 impact assessment and Phase 2 roadmap slot | I33: =IFERROR(INDEX('Stakeholder Register'!$T$5:$T$54,MATCH(LARGE('Stakeholder Register'!$Z$5:$Z$54,1),'Stakeholder Register'!$Z$5:$Z$54,0)),"") -> 46276
B34: =IFERROR(INDEX('Stakeholder Register'!$A$5:$A$54,MATCH(LARGE('Stakeholder Register'!$Z$5:$Z$54,2),'Stakeholder Register'!$Z$5:$Z$54,0)),"") -> SH-14 | C34: =IFERROR(INDEX('Stakeholder Register'!$B$5:$B$54,MATCH(LARGE('Stakeholder Register'!$Z$5:$Z$54,2),'Stakeholder Register'!$Z$5:$Z$54,0)),"") -> Marketing and Merchant Communications Lead | D34: =IFERROR(INDEX('Stakeholder Register'!$H$5:$H$54,MATCH(LARGE('Stakeholder Register'!$Z$5:$Z$54,2),'Stakeholder Register'!$Z$5:$Z$54,0)),"") -> Unaware | E34: =IFERROR(INDEX('Stakeholder Register'!$I$5:$I$54,MATCH(LARGE('Stakeholder Register'!$Z$5:$Z$54,2),'Stakeholder Register'!$Z$5:$Z$54,0)),"") -> Supportive | F34: =IFERROR(INDEX('Stakeholder Register'!$J$5:$J$54,MATCH(LARGE('Stakeholder Register'!$Z$5:$Z$54,2),'Stakeholder Register'!$Z$5:$Z$54,0)),"") -> 3 | G34: =IFERROR(INDEX('Stakeholder Register'!$S$5:$S$54,MATCH(LARGE('Stakeholder Register'!$Z$5:$Z$54,2),'Stakeholder Register'!$Z$5:$Z$54,0)),"") -> First briefing on GTM plan | I34: =IFERROR(INDEX('Stakeholder Register'!$T$5:$T$54,MATCH(LARGE('Stakeholder Register'!$Z$5:$Z$54,2),'Stakeholder Register'!$Z$5:$Z$54,0)),"") -> 46300
B35: =IFERROR(INDEX('Stakeholder Register'!$A$5:$A$54,MATCH(LARGE('Stakeholder Register'!$Z$5:$Z$54,3),'Stakeholder Register'!$Z$5:$Z$54,0)),"") -> SH-17 | C35: =IFERROR(INDEX('Stakeholder Register'!$B$5:$B$54,MATCH(LARGE('Stakeholder Register'!$Z$5:$Z$54,3),'Stakeholder Register'!$Z$5:$Z$54,0)),"") -> Pilot merchants (10) | D35: =IFERROR(INDEX('Stakeholder Register'!$H$5:$H$54,MATCH(LARGE('Stakeholder Register'!$Z$5:$Z$54,3),'Stakeholder Register'!$Z$5:$Z$54,0)),"") -> Unaware | E35: =IFERROR(INDEX('Stakeholder Register'!$I$5:$I$54,MATCH(LARGE('Stakeholder Register'!$Z$5:$Z$54,3),'Stakeholder Register'!$Z$5:$Z$54,0)),"") -> Supportive | F35: =IFERROR(INDEX('Stakeholder Register'!$J$5:$J$54,MATCH(LARGE('Stakeholder Register'!$Z$5:$Z$54,3),'Stakeholder Register'!$Z$5:$Z$54,0)),"") -> 3 | G35: =IFERROR(INDEX('Stakeholder Register'!$S$5:$S$54,MATCH(LARGE('Stakeholder Register'!$Z$5:$Z$54,3),'Stakeholder Register'!$Z$5:$Z$54,0)),"") -> Send pilot invitations once terms are approved | I35: =IFERROR(INDEX('Stakeholder Register'!$T$5:$T$54,MATCH(LARGE('Stakeholder Register'!$Z$5:$Z$54,3),'Stakeholder Register'!$Z$5:$Z$54,0)),"") -> 46328
B36: =IFERROR(INDEX('Stakeholder Register'!$A$5:$A$54,MATCH(LARGE('Stakeholder Register'!$Z$5:$Z$54,4),'Stakeholder Register'!$Z$5:$Z$54,0)),"") -> SH-01 | C36: =IFERROR(INDEX('Stakeholder Register'!$B$5:$B$54,MATCH(LARGE('Stakeholder Register'!$Z$5:$Z$54,4),'Stakeholder Register'!$Z$5:$Z$54,0)),"") -> Business Sponsor (Head of Merchant Services) | D36: =IFERROR(INDEX('Stakeholder Register'!$H$5:$H$54,MATCH(LARGE('Stakeholder Register'!$Z$5:$Z$54,4),'Stakeholder Register'!$Z$5:$Z$54,0)),"") -> Supportive | E36: =IFERROR(INDEX('Stakeholder Register'!$I$5:$I$54,MATCH(LARGE('Stakeholder Register'!$Z$5:$Z$54,4),'Stakeholder Register'!$Z$5:$Z$54,0)),"") -> Leading | F36: =IFERROR(INDEX('Stakeholder Register'!$J$5:$J$54,MATCH(LARGE('Stakeholder Register'!$Z$5:$Z$54,4),'Stakeholder Register'!$Z$5:$Z$54,0)),"") -> 1 | G36: =IFERROR(INDEX('Stakeholder Register'!$S$5:$S$54,MATCH(LARGE('Stakeholder Register'!$Z$5:$Z$54,4),'Stakeholder Register'!$Z$5:$Z$54,0)),"") -> Pre-wire CR-01 Option C and business case before steering committee | I36: =IFERROR(INDEX('Stakeholder Register'!$T$5:$T$54,MATCH(LARGE('Stakeholder Register'!$Z$5:$Z$54,4),'Stakeholder Register'!$Z$5:$Z$54,0)),"") -> 46279
B37: =IFERROR(INDEX('Stakeholder Register'!$A$5:$A$54,MATCH(LARGE('Stakeholder Register'!$Z$5:$Z$54,5),'Stakeholder Register'!$Z$5:$Z$54,0)),"") -> SH-02 | C37: =IFERROR(INDEX('Stakeholder Register'!$B$5:$B$54,MATCH(LARGE('Stakeholder Register'!$Z$5:$Z$54,5),'Stakeholder Register'!$Z$5:$Z$54,0)),"") -> Steering Committee (finance, technology and risk delegates) | D37: =IFERROR(INDEX('Stakeholder Register'!$H$5:$H$54,MATCH(LARGE('Stakeholder Register'!$Z$5:$Z$54,5),'Stakeholder Register'!$Z$5:$Z$54,0)),"") -> Neutral | E37: =IFERROR(INDEX('Stakeholder Register'!$I$5:$I$54,MATCH(LARGE('Stakeholder Register'!$Z$5:$Z$54,5),'Stakeholder Register'!$Z$5:$Z$54,0)),"") -> Supportive | F37: =IFERROR(INDEX('Stakeholder Register'!$J$5:$J$54,MATCH(LARGE('Stakeholder Register'!$Z$5:$Z$54,5),'Stakeholder Register'!$Z$5:$Z$54,0)),"") -> 1 | G37: =IFERROR(INDEX('Stakeholder Register'!$S$5:$S$54,MATCH(LARGE('Stakeholder Register'!$Z$5:$Z$54,5),'Stakeholder Register'!$Z$5:$Z$54,0)),"") -> Circulate pre-read two days before next meeting | I37: =IFERROR(INDEX('Stakeholder Register'!$T$5:$T$54,MATCH(LARGE('Stakeholder Register'!$Z$5:$Z$54,5),'Stakeholder Register'!$Z$5:$Z$54,0)),"") -> 46287
B38: =IFERROR(INDEX('Stakeholder Register'!$A$5:$A$54,MATCH(LARGE('Stakeholder Register'!$Z$5:$Z$54,6),'Stakeholder Register'!$Z$5:$Z$54,0)),"") -> SH-03 | C38: =IFERROR(INDEX('Stakeholder Register'!$B$5:$B$54,MATCH(LARGE('Stakeholder Register'!$Z$5:$Z$54,6),'Stakeholder Register'!$Z$5:$Z$54,0)),"") -> Dispute Ops Lead | D38: =IFERROR(INDEX('Stakeholder Register'!$H$5:$H$54,MATCH(LARGE('Stakeholder Register'!$Z$5:$Z$54,6),'Stakeholder Register'!$Z$5:$Z$54,0)),"") -> Supportive | E38: =IFERROR(INDEX('Stakeholder Register'!$I$5:$I$54,MATCH(LARGE('Stakeholder Register'!$Z$5:$Z$54,6),'Stakeholder Register'!$Z$5:$Z$54,0)),"") -> Leading | F38: =IFERROR(INDEX('Stakeholder Register'!$J$5:$J$54,MATCH(LARGE('Stakeholder Register'!$Z$5:$Z$54,6),'Stakeholder Register'!$Z$5:$Z$54,0)),"") -> 1 | G38: =IFERROR(INDEX('Stakeholder Register'!$S$5:$S$54,MATCH(LARGE('Stakeholder Register'!$Z$5:$Z$54,6),'Stakeholder Register'!$Z$5:$Z$54,0)),"") -> Confirm UAT SME bookings for November | I38: =IFERROR(INDEX('Stakeholder Register'!$T$5:$T$54,MATCH(LARGE('Stakeholder Register'!$Z$5:$Z$54,6),'Stakeholder Register'!$Z$5:$Z$54,0)),"") -> 46283
B40: Governance in the next 14 days
B41: Date | C41: Forum | E41: Chair | F41: Decisions and outputs | I41: Days until
B42: =IFERROR(INDEX(Governance!$I$5:$I$34,MATCH(SMALL(Governance!$K$5:$K$34,1),Governance!$K$5:$K$34,0)),"") -> 46276 | C42: =IFERROR(INDEX(Governance!$A$5:$A$34,MATCH(SMALL(Governance!$K$5:$K$34,1),Governance!$K$5:$K$34,0)),"") -> Sprint review | E42: =IFERROR(INDEX(Governance!$C$5:$C$34,MATCH(SMALL(Governance!$K$5:$K$34,1),Governance!$K$5:$K$34,0)),"") -> Product Owner | F42: =IFERROR(INDEX(Governance!$H$5:$H$34,MATCH(SMALL(Governance!$K$5:$K$34,1),Governance!$K$5:$K$34,0)),"") -> Accepted stories; backlog changes | I42: =IFERROR(INDEX(Governance!$J$5:$J$34,MATCH(SMALL(Governance!$K$5:$K$34,1),Governance!$K$5:$K$34,0)),"") -> 1
B43: =IFERROR(INDEX(Governance!$I$5:$I$34,MATCH(SMALL(Governance!$K$5:$K$34,2),Governance!$K$5:$K$34,0)),"") -> 46279 | C43: =IFERROR(INDEX(Governance!$A$5:$A$34,MATCH(SMALL(Governance!$K$5:$K$34,2),Governance!$K$5:$K$34,0)),"") -> Sponsor 1:1 | E43: =IFERROR(INDEX(Governance!$C$5:$C$34,MATCH(SMALL(Governance!$K$5:$K$34,2),Governance!$K$5:$K$34,0)),"") -> Engagement Lead | F43: =IFERROR(INDEX(Governance!$H$5:$H$34,MATCH(SMALL(Governance!$K$5:$K$34,2),Governance!$K$5:$K$34,0)),"") -> Medium-impact change decisions; escalation support | I43: =IFERROR(INDEX(Governance!$J$5:$J$34,MATCH(SMALL(Governance!$K$5:$K$34,2),Governance!$K$5:$K$34,0)),"") -> 4
B44: =IFERROR(INDEX(Governance!$I$5:$I$34,MATCH(SMALL(Governance!$K$5:$K$34,3),Governance!$K$5:$K$34,0)),"") -> 46279 | C44: =IFERROR(INDEX(Governance!$A$5:$A$34,MATCH(SMALL(Governance!$K$5:$K$34,3),Governance!$K$5:$K$34,0)),"") -> Sprint planning | E44: =IFERROR(INDEX(Governance!$C$5:$C$34,MATCH(SMALL(Governance!$K$5:$K$34,3),Governance!$K$5:$K$34,0)),"") -> Product Owner | F44: =IFERROR(INDEX(Governance!$H$5:$H$34,MATCH(SMALL(Governance!$K$5:$K$34,3),Governance!$K$5:$K$34,0)),"") -> Sprint goal and committed items | I44: =IFERROR(INDEX(Governance!$J$5:$J$34,MATCH(SMALL(Governance!$K$5:$K$34,3),Governance!$K$5:$K$34,0)),"") -> 4
B45: =IFERROR(INDEX(Governance!$I$5:$I$34,MATCH(SMALL(Governance!$K$5:$K$34,4),Governance!$K$5:$K$34,0)),"") -> 46280 | C45: =IFERROR(INDEX(Governance!$A$5:$A$34,MATCH(SMALL(Governance!$K$5:$K$34,4),Governance!$K$5:$K$34,0)),"") -> Backlog refinement | E45: =IFERROR(INDEX(Governance!$C$5:$C$34,MATCH(SMALL(Governance!$K$5:$K$34,4),Governance!$K$5:$K$34,0)),"") -> Product Owner | F45: =IFERROR(INDEX(Governance!$H$5:$H$34,MATCH(SMALL(Governance!$K$5:$K$34,4),Governance!$K$5:$K$34,0)),"") -> Refined and estimated stories | I45: =IFERROR(INDEX(Governance!$J$5:$J$34,MATCH(SMALL(Governance!$K$5:$K$34,4),Governance!$K$5:$K$34,0)),"") -> 5
B46: =IFERROR(INDEX(Governance!$I$5:$I$34,MATCH(SMALL(Governance!$K$5:$K$34,5),Governance!$K$5:$K$34,0)),"") -> 46280 | C46: =IFERROR(INDEX(Governance!$A$5:$A$34,MATCH(SMALL(Governance!$K$5:$K$34,5),Governance!$K$5:$K$34,0)),"") -> Design authority | E46: =IFERROR(INDEX(Governance!$C$5:$C$34,MATCH(SMALL(Governance!$K$5:$K$34,5),Governance!$K$5:$K$34,0)),"") -> Tech Lead | F46: =IFERROR(INDEX(Governance!$H$5:$H$34,MATCH(SMALL(Governance!$K$5:$K$34,5),Governance!$K$5:$K$34,0)),"") -> Design sign-off (I-03); architecture decisions | I46: =IFERROR(INDEX(Governance!$J$5:$J$34,MATCH(SMALL(Governance!$K$5:$K$34,5),Governance!$K$5:$K$34,0)),"") -> 5
B47: =IFERROR(INDEX(Governance!$I$5:$I$34,MATCH(SMALL(Governance!$K$5:$K$34,6),Governance!$K$5:$K$34,0)),"") -> 46280 | C47: =IFERROR(INDEX(Governance!$A$5:$A$34,MATCH(SMALL(Governance!$K$5:$K$34,6),Governance!$K$5:$K$34,0)),"") -> Processor vendor sync | E47: =IFERROR(INDEX(Governance!$C$5:$C$34,MATCH(SMALL(Governance!$K$5:$K$34,6),Governance!$K$5:$K$34,0)),"") -> Project Manager | F47: =IFERROR(INDEX(Governance!$H$5:$H$34,MATCH(SMALL(Governance!$K$5:$K$34,6),Governance!$K$5:$K$34,0)),"") -> Vendor actions and dates; escalation if dates slip | I47: =IFERROR(INDEX(Governance!$J$5:$J$34,MATCH(SMALL(Governance!$K$5:$K$34,6),Governance!$K$5:$K$34,0)),"") -> 5
B48: =IFERROR(INDEX(Governance!$I$5:$I$34,MATCH(SMALL(Governance!$K$5:$K$34,7),Governance!$K$5:$K$34,0)),"") -> 46281 | C48: =IFERROR(INDEX(Governance!$A$5:$A$34,MATCH(SMALL(Governance!$K$5:$K$34,7),Governance!$K$5:$K$34,0)),"") -> Weekly status and RAID / change review | E48: =IFERROR(INDEX(Governance!$C$5:$C$34,MATCH(SMALL(Governance!$K$5:$K$34,7),Governance!$K$5:$K$34,0)),"") -> Project Manager | F48: =IFERROR(INDEX(Governance!$H$5:$H$34,MATCH(SMALL(Governance!$K$5:$K$34,7),Governance!$K$5:$K$34,0)),"") -> Owners and dates for actions; items to escalate | I48: =IFERROR(INDEX(Governance!$J$5:$J$34,MATCH(SMALL(Governance!$K$5:$K$34,7),Governance!$K$5:$K$34,0)),"") -> 6
B49: =IFERROR(INDEX(Governance!$I$5:$I$34,MATCH(SMALL(Governance!$K$5:$K$34,8),Governance!$K$5:$K$34,0)),"") -> 46281 | C49: =IFERROR(INDEX(Governance!$A$5:$A$34,MATCH(SMALL(Governance!$K$5:$K$34,8),Governance!$K$5:$K$34,0)),"") -> Compliance and security checkpoint | E49: =IFERROR(INDEX(Governance!$C$5:$C$34,MATCH(SMALL(Governance!$K$5:$K$34,8),Governance!$K$5:$K$34,0)),"") -> Compliance Lead | F49: =IFERROR(INDEX(Governance!$H$5:$H$34,MATCH(SMALL(Governance!$K$5:$K$34,8),Governance!$K$5:$K$34,0)),"") -> Evidence gaps closed; compliance risks escalated | I49: =IFERROR(INDEX(Governance!$J$5:$J$34,MATCH(SMALL(Governance!$K$5:$K$34,8),Governance!$K$5:$K$34,0)),"") -> 6
B50: =IFERROR(INDEX(Governance!$I$5:$I$34,MATCH(SMALL(Governance!$K$5:$K$34,9),Governance!$K$5:$K$34,0)),"") -> 46282 | C50: =IFERROR(INDEX(Governance!$A$5:$A$34,MATCH(SMALL(Governance!$K$5:$K$34,9),Governance!$K$5:$K$34,0)),"") -> Outcome definitions decision meeting | E50: =IFERROR(INDEX(Governance!$C$5:$C$34,MATCH(SMALL(Governance!$K$5:$K$34,9),Governance!$K$5:$K$34,0)),"") -> Business Sponsor | F50: =IFERROR(INDEX(Governance!$H$5:$H$34,MATCH(SMALL(Governance!$K$5:$K$34,9),Governance!$K$5:$K$34,0)),"") -> CR-05 decision; KPI-01 and KPI-02 status updated | I50: =IFERROR(INDEX(Governance!$J$5:$J$34,MATCH(SMALL(Governance!$K$5:$K$34,9),Governance!$K$5:$K$34,0)),"") -> 7
B51: =IFERROR(INDEX(Governance!$I$5:$I$34,MATCH(SMALL(Governance!$K$5:$K$34,10),Governance!$K$5:$K$34,0)),"") -> 46289 | C51: =IFERROR(INDEX(Governance!$A$5:$A$34,MATCH(SMALL(Governance!$K$5:$K$34,10),Governance!$K$5:$K$34,0)),"") -> Steering Committee | E51: =IFERROR(INDEX(Governance!$C$5:$C$34,MATCH(SMALL(Governance!$K$5:$K$34,10),Governance!$K$5:$K$34,0)),"") -> Business Sponsor | F51: =IFERROR(INDEX(Governance!$H$5:$H$34,MATCH(SMALL(Governance!$K$5:$K$34,10),Governance!$K$5:$K$34,0)),"") -> Approve High-impact changes, go / no-go decisions, escalations | I51: =IFERROR(INDEX(Governance!$J$5:$J$34,MATCH(SMALL(Governance!$K$5:$K$34,10),Governance!$K$5:$K$34,0)),"") -> 14
B53: Deliverables due in the next 30 days (not yet approved)
B54: ID | C54: Deliverable | E54: Owner | F54: Approver | G54: Due | H54: Status | I54: Overdue?
B55: =IFERROR(INDEX(Deliverables!$A$5:$A$54,MATCH(SMALL(Deliverables!$K$5:$K$54,1),Deliverables!$K$5:$K$54,0)),"") -> DL-07 | C55: =IFERROR(INDEX(Deliverables!$B$5:$B$54,MATCH(SMALL(Deliverables!$K$5:$K$54,1),Deliverables!$K$5:$K$54,0)),"") -> Figma MVP designs | E55: =IFERROR(INDEX(Deliverables!$E$5:$E$54,MATCH(SMALL(Deliverables!$K$5:$K$54,1),Deliverables!$K$5:$K$54,0)),"") -> UX Designer | F55: =IFERROR(INDEX(Deliverables!$F$5:$F$54,MATCH(SMALL(Deliverables!$K$5:$K$54,1),Deliverables!$K$5:$K$54,0)),"") -> Design authority | G55: =IFERROR(INDEX(Deliverables!$G$5:$G$54,MATCH(SMALL(Deliverables!$K$5:$K$54,1),Deliverables!$K$5:$K$54,0)),"") -> 46280 | H55: =IFERROR(INDEX(Deliverables!$H$5:$H$54,MATCH(SMALL(Deliverables!$K$5:$K$54,1),Deliverables!$K$5:$K$54,0)),"") -> In Review | I55: =IFERROR(INDEX(Deliverables!$J$5:$J$54,MATCH(SMALL(Deliverables!$K$5:$K$54,1),Deliverables!$K$5:$K$54,0)),"") -> No
B56: =IFERROR(INDEX(Deliverables!$A$5:$A$54,MATCH(SMALL(Deliverables!$K$5:$K$54,2),Deliverables!$K$5:$K$54,0)),"") -> DL-11 | C56: =IFERROR(INDEX(Deliverables!$B$5:$B$54,MATCH(SMALL(Deliverables!$K$5:$K$54,2),Deliverables!$K$5:$K$54,0)),"") -> Stakeholder engagement plan | E56: =IFERROR(INDEX(Deliverables!$E$5:$E$54,MATCH(SMALL(Deliverables!$K$5:$K$54,2),Deliverables!$K$5:$K$54,0)),"") -> Product Owner and Engagement Lead | F56: =IFERROR(INDEX(Deliverables!$F$5:$F$54,MATCH(SMALL(Deliverables!$K$5:$K$54,2),Deliverables!$K$5:$K$54,0)),"") -> Business Sponsor | G56: =IFERROR(INDEX(Deliverables!$G$5:$G$54,MATCH(SMALL(Deliverables!$K$5:$K$54,2),Deliverables!$K$5:$K$54,0)),"") -> 46282 | H56: =IFERROR(INDEX(Deliverables!$H$5:$H$54,MATCH(SMALL(Deliverables!$K$5:$K$54,2),Deliverables!$K$5:$K$54,0)),"") -> In Review | I56: =IFERROR(INDEX(Deliverables!$J$5:$J$54,MATCH(SMALL(Deliverables!$K$5:$K$54,2),Deliverables!$K$5:$K$54,0)),"") -> No
B57: =IFERROR(INDEX(Deliverables!$A$5:$A$54,MATCH(SMALL(Deliverables!$K$5:$K$54,3),Deliverables!$K$5:$K$54,0)),"") -> DL-09 | C57: =IFERROR(INDEX(Deliverables!$B$5:$B$54,MATCH(SMALL(Deliverables!$K$5:$K$54,3),Deliverables!$K$5:$K$54,0)),"") -> KPI and metrics definitions | E57: =IFERROR(INDEX(Deliverables!$E$5:$E$54,MATCH(SMALL(Deliverables!$K$5:$K$54,3),Deliverables!$K$5:$K$54,0)),"") -> Product Owner | F57: =IFERROR(INDEX(Deliverables!$F$5:$F$54,MATCH(SMALL(Deliverables!$K$5:$K$54,3),Deliverables!$K$5:$K$54,0)),"") -> Business Sponsor | G57: =IFERROR(INDEX(Deliverables!$G$5:$G$54,MATCH(SMALL(Deliverables!$K$5:$K$54,3),Deliverables!$K$5:$K$54,0)),"") -> 46283 | H57: =IFERROR(INDEX(Deliverables!$H$5:$H$54,MATCH(SMALL(Deliverables!$K$5:$K$54,3),Deliverables!$K$5:$K$54,0)),"") -> In Review | I57: =IFERROR(INDEX(Deliverables!$J$5:$J$54,MATCH(SMALL(Deliverables!$K$5:$K$54,3),Deliverables!$K$5:$K$54,0)),"") -> No
B58: =IFERROR(INDEX(Deliverables!$A$5:$A$54,MATCH(SMALL(Deliverables!$K$5:$K$54,4),Deliverables!$K$5:$K$54,0)),"") -> DL-10 | C58: =IFERROR(INDEX(Deliverables!$B$5:$B$54,MATCH(SMALL(Deliverables!$K$5:$K$54,4),Deliverables!$K$5:$K$54,0)),"") -> Business case and GTM plan | E58: =IFERROR(INDEX(Deliverables!$E$5:$E$54,MATCH(SMALL(Deliverables!$K$5:$K$54,4),Deliverables!$K$5:$K$54,0)),"") -> Product Owner | F58: =IFERROR(INDEX(Deliverables!$F$5:$F$54,MATCH(SMALL(Deliverables!$K$5:$K$54,4),Deliverables!$K$5:$K$54,0)),"") -> Steering Committee | G58: =IFERROR(INDEX(Deliverables!$G$5:$G$54,MATCH(SMALL(Deliverables!$K$5:$K$54,4),Deliverables!$K$5:$K$54,0)),"") -> 46289 | H58: =IFERROR(INDEX(Deliverables!$H$5:$H$54,MATCH(SMALL(Deliverables!$K$5:$K$54,4),Deliverables!$K$5:$K$54,0)),"") -> In Review | I58: =IFERROR(INDEX(Deliverables!$J$5:$J$54,MATCH(SMALL(Deliverables!$K$5:$K$54,4),Deliverables!$K$5:$K$54,0)),"") -> No
B59: =IFERROR(INDEX(Deliverables!$A$5:$A$54,MATCH(SMALL(Deliverables!$K$5:$K$54,5),Deliverables!$K$5:$K$54,0)),"") | C59: =IFERROR(INDEX(Deliverables!$B$5:$B$54,MATCH(SMALL(Deliverables!$K$5:$K$54,5),Deliverables!$K$5:$K$54,0)),"") | E59: =IFERROR(INDEX(Deliverables!$E$5:$E$54,MATCH(SMALL(Deliverables!$K$5:$K$54,5),Deliverables!$K$5:$K$54,0)),"") | F59: =IFERROR(INDEX(Deliverables!$F$5:$F$54,MATCH(SMALL(Deliverables!$K$5:$K$54,5),Deliverables!$K$5:$K$54,0)),"") | G59: =IFERROR(INDEX(Deliverables!$G$5:$G$54,MATCH(SMALL(Deliverables!$K$5:$K$54,5),Deliverables!$K$5:$K$54,0)),"") | H59: =IFERROR(INDEX(Deliverables!$H$5:$H$54,MATCH(SMALL(Deliverables!$K$5:$K$54,5),Deliverables!$K$5:$K$54,0)),"") | I59: =IFERROR(INDEX(Deliverables!$J$5:$J$54,MATCH(SMALL(Deliverables!$K$5:$K$54,5),Deliverables!$K$5:$K$54,0)),"")
B60: =IFERROR(INDEX(Deliverables!$A$5:$A$54,MATCH(SMALL(Deliverables!$K$5:$K$54,6),Deliverables!$K$5:$K$54,0)),"") | C60: =IFERROR(INDEX(Deliverables!$B$5:$B$54,MATCH(SMALL(Deliverables!$K$5:$K$54,6),Deliverables!$K$5:$K$54,0)),"") | E60: =IFERROR(INDEX(Deliverables!$E$5:$E$54,MATCH(SMALL(Deliverables!$K$5:$K$54,6),Deliverables!$K$5:$K$54,0)),"") | F60: =IFERROR(INDEX(Deliverables!$F$5:$F$54,MATCH(SMALL(Deliverables!$K$5:$K$54,6),Deliverables!$K$5:$K$54,0)),"") | G60: =IFERROR(INDEX(Deliverables!$G$5:$G$54,MATCH(SMALL(Deliverables!$K$5:$K$54,6),Deliverables!$K$5:$K$54,0)),"") | H60: =IFERROR(INDEX(Deliverables!$H$5:$H$54,MATCH(SMALL(Deliverables!$K$5:$K$54,6),Deliverables!$K$5:$K$54,0)),"") | I60: =IFERROR(INDEX(Deliverables!$J$5:$J$54,MATCH(SMALL(Deliverables!$K$5:$K$54,6),Deliverables!$K$5:$K$54,0)),"")
B62: Engagement health by stakeholder type
B63: Type | D63: Stakeholders | E63: Manage closely | F63: With gap | G63: Resistant or unaware | H63: Overdue actions
B64: Client | D64: =COUNTIFS('Stakeholder Register'!$D$5:$D$54,"Client") -> 14 | E64: =COUNTIFS('Stakeholder Register'!$D$5:$D$54,"Client",'Stakeholder Register'!$G$5:$G$54,"Manage closely") -> 5 | F64: =COUNTIFS('Stakeholder Register'!$D$5:$D$54,"Client",'Stakeholder Register'!$J$5:$J$54,">0") -> 12 | G64: =COUNTIFS('Stakeholder Register'!$D$5:$D$54,"Client",'Stakeholder Register'!$H$5:$H$54,"Resistant")+COUNTIFS('Stakeholder Register'!$D$5:$D$54,"Client",'Stakeholder Register'!$H$5:$H$54,"Unaware") -> 2 | H64: =COUNTIFS('Stakeholder Register'!$D$5:$D$54,"Client",'Stakeholder Register'!$U$5:$U$54,"Overdue") -> 0
B65: Vendor | D65: =COUNTIFS('Stakeholder Register'!$D$5:$D$54,"Vendor") -> 2 | E65: =COUNTIFS('Stakeholder Register'!$D$5:$D$54,"Vendor",'Stakeholder Register'!$G$5:$G$54,"Manage closely") -> 0 | F65: =COUNTIFS('Stakeholder Register'!$D$5:$D$54,"Vendor",'Stakeholder Register'!$J$5:$J$54,">0") -> 1 | G65: =COUNTIFS('Stakeholder Register'!$D$5:$D$54,"Vendor",'Stakeholder Register'!$H$5:$H$54,"Resistant")+COUNTIFS('Stakeholder Register'!$D$5:$D$54,"Vendor",'Stakeholder Register'!$H$5:$H$54,"Unaware") -> 0 | H65: =COUNTIFS('Stakeholder Register'!$D$5:$D$54,"Vendor",'Stakeholder Register'!$U$5:$U$54,"Overdue") -> 1
B66: External | D66: =COUNTIFS('Stakeholder Register'!$D$5:$D$54,"External") -> 1 | E66: =COUNTIFS('Stakeholder Register'!$D$5:$D$54,"External",'Stakeholder Register'!$G$5:$G$54,"Manage closely") -> 0 | F66: =COUNTIFS('Stakeholder Register'!$D$5:$D$54,"External",'Stakeholder Register'!$J$5:$J$54,">0") -> 1 | G66: =COUNTIFS('Stakeholder Register'!$D$5:$D$54,"External",'Stakeholder Register'!$H$5:$H$54,"Resistant")+COUNTIFS('Stakeholder Register'!$D$5:$D$54,"External",'Stakeholder Register'!$H$5:$H$54,"Unaware") -> 1 | H66: =COUNTIFS('Stakeholder Register'!$D$5:$D$54,"External",'Stakeholder Register'!$U$5:$U$54,"Overdue") -> 0
B67: Delivery partner | D67: =COUNTIFS('Stakeholder Register'!$D$5:$D$54,"Delivery partner") -> 1 | E67: =COUNTIFS('Stakeholder Register'!$D$5:$D$54,"Delivery partner",'Stakeholder Register'!$G$5:$G$54,"Manage closely") -> 0 | F67: =COUNTIFS('Stakeholder Register'!$D$5:$D$54,"Delivery partner",'Stakeholder Register'!$J$5:$J$54,">0") -> 0 | G67: =COUNTIFS('Stakeholder Register'!$D$5:$D$54,"Delivery partner",'Stakeholder Register'!$H$5:$H$54,"Resistant")+COUNTIFS('Stakeholder Register'!$D$5:$D$54,"Delivery partner",'Stakeholder Register'!$H$5:$H$54,"Unaware") -> 0 | H67: =COUNTIFS('Stakeholder Register'!$D$5:$D$54,"Delivery partner",'Stakeholder Register'!$U$5:$U$54,"Overdue") -> 0

Sheet Engagement Overview
A1: Engagement Overview
A2: Merchant Payment Operations & Dispute Hub · Simulation project
A4: Engagement summary
A5: Topic | B5: Summary
A6: Client context | B6: Merchant services division of a card payments provider (illustrative), supporting about 25,000 active merchants.
A7: Problem | B7: Merchants manage disputes by email and spreadsheets. Deadlines are missed, evidence is chased manually, ops handling time is high and settlement changes are hard to explain.
A8: Objectives | B8: 1. Give merchants self-service dispute tracking and evidence submission. 2. Cut ops handling time and missed-deadline losses. 3. Keep card data out of evidence storage. 4. Give ops and finance one trusted set of dispute numbers.
A9: In scope (MVP) | B9: Merchant portal (inbox, dispute detail, evidence upload and submission), processor integration, reminders, settlement visibility, ops work queue, reporting, servicing status API.
A10: Out of scope | B10: Fraud case management (Phase 2, CR-01), Spanish portal (Phase 2, CR-04), marketplace sub-merchant model, SMS reminders pending CR-09.
A11: Delivery approach | B11: Agile delivery in two-week sprints with a pilot-led rollout; governance through sponsor 1:1s, fortnightly steering committee and weekly RAID and change review.
A12: Key constraints | B12: Q4 dispute peak limits SME time (R-06); holiday change freeze after go-live; security and compliance gates before launch (D-03, CR-03).
A13: Success criteria | B13: MVP live by 11-Dec-2026; pilot exit gates met; base-case KPI targets by mid-2027 (KPI-03 on-time response 95%, KPI-05 handling time 25 min, KPI-06 portal share 70%).
A15: Phases
A16: Phase | B16: Dates | C16: Focus | E16: Key outputs
A17: Discovery | B17: Jun – Jul 2026 | C17: Merchant and ops research; problem and opportunity sizing | E17: Discovery findings; MVP scope baseline
A18: Mobilization and design | B18: Jul – Aug 2026 | C18: Team setup, solution design, governance, RAID and change control | E18: Solution design; RAID and change logs; engagement plan
A19: Build | B19: 20-Jul – 04-Dec 2026 | C19: Sprints 1–10; SIT, security and accessibility testing; UAT | E19: Working MVP; RTM; KPI definitions; business case
A20: Launch and pilot | B20: Dec 2026 – Mar 2027 | C20: Go-live, hypercare, 10-merchant pilot | E20: Go-live readiness pack; pilot results report
A21: Scale | B21: Mar – Dec 2027 | C21: Wave 1, Wave 2, general availability; email intake retirement | E21: Wave go / no-go packs; benefits tracking
A23: Engagement team model
A24: Role | B24: Organization | C24: Responsibilities | F24: Allocation
A25: Business Sponsor | B25: Client | C25: Funding, priorities, Medium-impact decisions, sponsor escalations | F25: As needed
A26: Engagement Lead | B26: Delivery partner | C26: Overall delivery accountability, sponsor relationship, commercial and quality oversight | F26: Part time
A27: Product Owner | B27: Delivery partner | C27: Product vision, backlog ownership, stakeholder alignment, acceptance, KPIs and business case | F27: Full time
A28: Project Manager | B28: Delivery partner | C28: Plan, RAID, change control, status reporting, vendor coordination | F28: Part time
A29: Business Analyst | B29: Delivery partner | C29: Requirements, process mapping, acceptance criteria, UAT support | F29: Full time
A30: Tech Lead | B30: Delivery partner | C30: Solution design, engineering delivery, technical risk | F30: Full time
A31: Delivery squads (Portal, Integration, Data) | B31: Delivery partner | C31: Build, test and release MVP features | F31: Full time
A32: QA Lead | B32: Delivery partner | C32: Test strategy, traceability, UAT coordination | F32: Full time
A33: UX Designer | B33: Delivery partner | C33: Research, designs, accessibility | F33: Part time
A34: Client SMEs (Dispute Ops, Finance, Compliance, Servicing) | B34: Client | C34: Process knowledge, requirement sign-off, UAT execution, readiness | F34: Part time (bookings agreed)

Sheet Stakeholder Register
A1: Stakeholder Register
A2: Merchant Payment Operations & Dispute Hub · Simulation project · Stakeholders are roles, not named individuals
A3: High influence / interest threshold (1–5): | E3: 4 | G3: Grey columns calculate automatically. Engagement gap = desired level − current level.
A4: ID | B4: Stakeholder | C4: Group | D4: Type | E4: Influence (1-5) | F4: Interest (1-5) | G4: Quadrant | H4: Current engagement | I4: Desired engagement | J4: Gap | K4: Priority score | L4: Interests and concerns | M4: Engagement strategy | N4: Relationship owner | O4: Frequency | P4: Channel | Q4: Linked items | R4: Last contact | S4: Next action | T4: Next action date | U4: Action overdue? | V4: h_mc | W4: h_ks | X4: h_ki | Y4: h_mon | Z4: h_gap
A5: SH-01 | B5: Business Sponsor (Head of Merchant Services) | C5: Merchant Services leadership | D5: Client | E5: 5 | F5: 4 | G5: =IF(A5="","",IF(AND(E5>=$E$3,F5>=$E$3),"Manage closely",IF(E5>=$E$3,"Keep satisfied",IF(F5>=$E$3,"Keep informed","Monitor")))) -> Manage closely | H5: Supportive | I5: Leading | J5: =IF(OR(A5="",H5="",I5=""),"",IF(I5="Unaware",1,IF(I5="Resistant",2,IF(I5="Neutral",3,IF(I5="Supportive",4,IF(I5="Leading",5,0)))))-IF(H5="Unaware",1,IF(H5="Resistant",2,IF(H5="Neutral",3,IF(H5="Supportive",4,IF(H5="Leading",5,0)))))) -> 1 | K5: =IF(J5="","",J5*E5) -> 5 | L5: Return on investment, go-live date, merchant experience, visible progress for leadership. | M5: Weekly 1:1; pre-wire every steering committee decision; share business case scenarios early so there are no surprises. | N5: Engagement Lead | O5: Weekly | P5: 1:1 meeting | Q5: CR-01, CR-05, Business case | R5: 46272 | S5: Pre-wire CR-01 Option C and business case before steering committee | T5: 46279 | U5: =IF(OR(A5="",T5=""),"",IF(T5<Cover!$C$7,"Overdue","No")) -> No | V5: =IF(G5="Manage closely",ROW(),"") -> 5 | W5: =IF(G5="Keep satisfied",ROW(),"") | X5: =IF(G5="Keep informed",ROW(),"") | Y5: =IF(G5="Monitor",ROW(),"") | Z5: =IF(OR(J5="",N(J5)<=0),"",K5+(1000-ROW())/100000) -> 5.00995
A6: SH-02 | B6: Steering Committee (finance, technology and risk delegates) | C6: Executive governance | D6: Client | E6: 5 | F6: 3 | G6: =IF(A6="","",IF(AND(E6>=$E$3,F6>=$E$3),"Manage closely",IF(E6>=$E$3,"Keep satisfied",IF(F6>=$E$3,"Keep informed","Monitor")))) -> Keep satisfied | H6: Neutral | I6: Supportive | J6: =IF(OR(A6="",H6="",I6=""),"",IF(I6="Unaware",1,IF(I6="Resistant",2,IF(I6="Neutral",3,IF(I6="Supportive",4,IF(I6="Leading",5,0)))))-IF(H6="Unaware",1,IF(H6="Resistant",2,IF(H6="Neutral",3,IF(H6="Supportive",4,IF(H6="Leading",5,0)))))) -> 1 | K6: =IF(J6="","",J6*E6) -> 5 | L6: Cost against contingency, security and compliance risk, delivery confidence. | M6: Fortnightly decision papers with clear options and recommendation; show conservative case openly; escalate only decisions that need them. | N6: Product Owner | O6: Fortnightly | P6: Steering committee | Q6: D-03, CR-06, Business case | R6: 46275 | S6: Circulate pre-read two days before next meeting | T6: 46287 | U6: =IF(OR(A6="",T6=""),"",IF(T6<Cover!$C$7,"Overdue","No")) -> No | V6: =IF(G6="Manage closely",ROW(),"") | W6: =IF(G6="Keep satisfied",ROW(),"") -> 6 | X6: =IF(G6="Keep informed",ROW(),"") | Y6: =IF(G6="Monitor",ROW(),"") | Z6: =IF(OR(J6="",N(J6)<=0),"",K6+(1000-ROW())/100000) -> 5.00994
A7: SH-03 | B7: Dispute Ops Lead | C7: Dispute Operations | D7: Client | E7: 4 | F7: 5 | G7: =IF(A7="","",IF(AND(E7>=$E$3,F7>=$E$3),"Manage closely",IF(E7>=$E$3,"Keep satisfied",IF(F7>=$E$3,"Keep informed","Monitor")))) -> Manage closely | H7: Supportive | I7: Leading | J7: =IF(OR(A7="",H7="",I7=""),"",IF(I7="Unaware",1,IF(I7="Resistant",2,IF(I7="Neutral",3,IF(I7="Supportive",4,IF(I7="Leading",5,0)))))-IF(H7="Unaware",1,IF(H7="Resistant",2,IF(H7="Neutral",3,IF(H7="Supportive",4,IF(H7="Leading",5,0)))))) -> 1 | K7: =IF(J7="","",J7*E7) -> 4 | L7: Team workload during Q4 peak, handling time, reliable deadlines for merchants. | M7: Co-design sessions; make them owner of UAT scenarios and ops readiness; protect SME time during peak (R-06). | N7: Product Owner | O7: Weekly | P7: Working session | Q7: R-06, KPI-05, I-02 | R7: 46274 | S7: Confirm UAT SME bookings for November | T7: 46283 | U7: =IF(OR(A7="",T7=""),"",IF(T7<Cover!$C$7,"Overdue","No")) -> No | V7: =IF(G7="Manage closely",ROW(),"") -> 7 | W7: =IF(G7="Keep satisfied",ROW(),"") | X7: =IF(G7="Keep informed",ROW(),"") | Y7: =IF(G7="Monitor",ROW(),"") | Z7: =IF(OR(J7="",N(J7)<=0),"",K7+(1000-ROW())/100000) -> 4.00993
A8: SH-04 | B8: Finance Lead | C8: Finance | D8: Client | E8: 4 | F8: 4 | G8: =IF(A8="","",IF(AND(E8>=$E$3,F8>=$E$3),"Manage closely",IF(E8>=$E$3,"Keep satisfied",IF(F8>=$E$3,"Keep informed","Monitor")))) -> Manage closely | H8: Neutral | I8: Supportive | J8: =IF(OR(A8="",H8="",I8=""),"",IF(I8="Unaware",1,IF(I8="Resistant",2,IF(I8="Neutral",3,IF(I8="Supportive",4,IF(I8="Leading",5,0)))))-IF(H8="Unaware",1,IF(H8="Resistant",2,IF(H8="Neutral",3,IF(H8="Supportive",4,IF(H8="Leading",5,0)))))) -> 1 | K8: =IF(J8="","",J8*E8) -> 4 | L8: How dispute outcomes and win rate are defined; whether ops savings are cashable; reconciliation accuracy. | M8: 1:1 using the outcome definitions worked example; involve in KPI sign-off; agree ops capacity treatment before Wave 1. | N8: Product Owner | O8: Weekly | P8: 1:1 meeting | Q8: CR-05, I-05, LR-17 | R8: 46273 | S8: Walk through outcome definitions worked example | T8: 46280 | U8: =IF(OR(A8="",T8=""),"",IF(T8<Cover!$C$7,"Overdue","No")) -> No | V8: =IF(G8="Manage closely",ROW(),"") -> 8 | W8: =IF(G8="Keep satisfied",ROW(),"") | X8: =IF(G8="Keep informed",ROW(),"") | Y8: =IF(G8="Monitor",ROW(),"") | Z8: =IF(OR(J8="",N(J8)<=0),"",K8+(1000-ROW())/100000) -> 4.00992
A9: SH-05 | B9: Fraud Operations Lead | C9: Fraud Operations | D9: Client | E9: 3 | F9: 4 | G9: =IF(A9="","",IF(AND(E9>=$E$3,F9>=$E$3),"Manage closely",IF(E9>=$E$3,"Keep satisfied",IF(F9>=$E$3,"Keep informed","Monitor")))) -> Keep informed | H9: Resistant | I9: Supportive | J9: =IF(OR(A9="",H9="",I9=""),"",IF(I9="Unaware",1,IF(I9="Resistant",2,IF(I9="Neutral",3,IF(I9="Supportive",4,IF(I9="Leading",5,0)))))-IF(H9="Unaware",1,IF(H9="Resistant",2,IF(H9="Neutral",3,IF(H9="Supportive",4,IF(H9="Leading",5,0)))))) -> 2 | K9: =IF(J9="","",J9*E9) -> 6 | L9: Wants fraud case management in the MVP; worried fraud context will be missed on disputes. | M9: Explain CR-01 options and impact; offer Option C read-only reference in MVP with a Phase 2 roadmap commitment; invite to sprint review. | N9: Product Owner | O9: Fortnightly | P9: Working session | Q9: CR-01, D-07, R-07 | R9: 46268 | S9: Share CR-01 impact assessment and Phase 2 roadmap slot | T9: 46276 | U9: =IF(OR(A9="",T9=""),"",IF(T9<Cover!$C$7,"Overdue","No")) -> No | V9: =IF(G9="Manage closely",ROW(),"") | W9: =IF(G9="Keep satisfied",ROW(),"") | X9: =IF(G9="Keep informed",ROW(),"") -> 9 | Y9: =IF(G9="Monitor",ROW(),"") | Z9: =IF(OR(J9="",N(J9)<=0),"",K9+(1000-ROW())/100000) -> 6.00991
A10: SH-06 | B10: Compliance Lead | C10: Compliance | D10: Client | E10: 5 | F10: 4 | G10: =IF(A10="","",IF(AND(E10>=$E$3,F10>=$E$3),"Manage closely",IF(E10>=$E$3,"Keep satisfied",IF(F10>=$E$3,"Keep informed","Monitor")))) -> Manage closely | H10: Supportive | I10: Supportive | J10: =IF(OR(A10="",H10="",I10=""),"",IF(I10="Unaware",1,IF(I10="Resistant",2,IF(I10="Neutral",3,IF(I10="Supportive",4,IF(I10="Leading",5,0)))))-IF(H10="Unaware",1,IF(H10="Resistant",2,IF(H10="Neutral",3,IF(H10="Supportive",4,IF(H10="Leading",5,0)))))) -> 0 | K10: =IF(J10="","",J10*E10) -> 0 | L10: PCI DSS scope, card data exposure, evidence retention, audit trail. | M10: Fortnightly checkpoint using the RTM control view; share evidence gaps early; no surprises at go-live. | N10: Product Owner | O10: Fortnightly | P10: Checkpoint meeting | Q10: R-02, CR-03, A-07, CTL-09 | R10: 46267 | S10: Review CTL-09 retention gap and A-07 timeline | T10: 46281 | U10: =IF(OR(A10="",T10=""),"",IF(T10<Cover!$C$7,"Overdue","No")) -> No | V10: =IF(G10="Manage closely",ROW(),"") -> 10 | W10: =IF(G10="Keep satisfied",ROW(),"") | X10: =IF(G10="Keep informed",ROW(),"") | Y10: =IF(G10="Monitor",ROW(),"") | Z10: =IF(OR(J10="",N(J10)<=0),"",K10+(1000-ROW())/100000)
A11: SH-07 | B11: InfoSec Lead | C11: Information Security | D11: Client | E11: 4 | F11: 3 | G11: =IF(A11="","",IF(AND(E11>=$E$3,F11>=$E$3),"Manage closely",IF(E11>=$E$3,"Keep satisfied",IF(F11>=$E$3,"Keep informed","Monitor")))) -> Keep satisfied | H11: Neutral | I11: Supportive | J11: =IF(OR(A11="",H11="",I11=""),"",IF(I11="Unaware",1,IF(I11="Resistant",2,IF(I11="Neutral",3,IF(I11="Supportive",4,IF(I11="Leading",5,0)))))-IF(H11="Unaware",1,IF(H11="Resistant",2,IF(H11="Neutral",3,IF(H11="Supportive",4,IF(H11="Leading",5,0)))))) -> 1 | K11: =IF(J11="","",J11*E11) -> 4 | L11: Pen test capacity, redaction validation effort, vendor security assessments. | M11: Share test scope and dates early; ask sponsor to support priority pen test slot; agree redaction validation test set. | N11: Project Manager | O11: Fortnightly | P11: Checkpoint meeting | Q11: D-03, LR-02, LR-03, R-08 | R11: 46269 | S11: Request priority pen test slot with sponsor support | T11: 46279 | U11: =IF(OR(A11="",T11=""),"",IF(T11<Cover!$C$7,"Overdue","No")) -> No | V11: =IF(G11="Manage closely",ROW(),"") | W11: =IF(G11="Keep satisfied",ROW(),"") -> 11 | X11: =IF(G11="Keep informed",ROW(),"") | Y11: =IF(G11="Monitor",ROW(),"") | Z11: =IF(OR(J11="",N(J11)<=0),"",K11+(1000-ROW())/100000) -> 4.00989
A12: SH-08 | B12: Legal Counsel | C12: Legal | D12: Client | E12: 3 | F12: 2 | G12: =IF(A12="","",IF(AND(E12>=$E$3,F12>=$E$3),"Manage closely",IF(E12>=$E$3,"Keep satisfied",IF(F12>=$E$3,"Keep informed","Monitor")))) -> Monitor | H12: Neutral | I12: Supportive | J12: =IF(OR(A12="",H12="",I12=""),"",IF(I12="Unaware",1,IF(I12="Resistant",2,IF(I12="Neutral",3,IF(I12="Supportive",4,IF(I12="Leading",5,0)))))-IF(H12="Unaware",1,IF(H12="Resistant",2,IF(H12="Neutral",3,IF(H12="Supportive",4,IF(H12="Leading",5,0)))))) -> 1 | K12: =IF(J12="","",J12*E12) -> 3 | L12: Merchant portal terms of use, data retention obligations. | M12: Book a fixed review slot with a short pre-read highlighting only decisions needed. | N12: Product Owner | O12: Monthly | P12: Email and meeting | Q12: D-05, A-07 | R12: 46273 | S12: Confirm legal review slot for terms of use | T12: 46282 | U12: =IF(OR(A12="",T12=""),"",IF(T12<Cover!$C$7,"Overdue","No")) -> No | V12: =IF(G12="Manage closely",ROW(),"") | W12: =IF(G12="Keep satisfied",ROW(),"") | X12: =IF(G12="Keep informed",ROW(),"") | Y12: =IF(G12="Monitor",ROW(),"") -> 12 | Z12: =IF(OR(J12="",N(J12)<=0),"",K12+(1000-ROW())/100000) -> 3.00988
A13: SH-09 | B13: IAM Team Lead | C13: Identity and Access Management | D13: Client | E13: 3 | F13: 2 | G13: =IF(A13="","",IF(AND(E13>=$E$3,F13>=$E$3),"Manage closely",IF(E13>=$E$3,"Keep satisfied",IF(F13>=$E$3,"Keep informed","Monitor")))) -> Monitor | H13: Supportive | I13: Supportive | J13: =IF(OR(A13="",H13="",I13=""),"",IF(I13="Unaware",1,IF(I13="Resistant",2,IF(I13="Neutral",3,IF(I13="Supportive",4,IF(I13="Leading",5,0)))))-IF(H13="Unaware",1,IF(H13="Resistant",2,IF(H13="Neutral",3,IF(H13="Supportive",4,IF(H13="Leading",5,0)))))) -> 0 | K13: =IF(J13="","",J13*E13) -> 0 | L13: Role configuration effort and timing. | M13: Keep the Tuesday joint checkpoint; confirm acceptance criteria for role setup. | N13: Tech Lead | O13: Weekly | P13: Checkpoint meeting | Q13: D-02, A-03 | R13: 46273 | S13: Confirm role configuration on track for 30-Sep | T13: 46280 | U13: =IF(OR(A13="",T13=""),"",IF(T13<Cover!$C$7,"Overdue","No")) -> No | V13: =IF(G13="Manage closely",ROW(),"") | W13: =IF(G13="Keep satisfied",ROW(),"") | X13: =IF(G13="Keep informed",ROW(),"") | Y13: =IF(G13="Monitor",ROW(),"") -> 13 | Z13: =IF(OR(J13="",N(J13)<=0),"",K13+(1000-ROW())/100000)
A14: SH-10 | B14: Data Engineering Lead | C14: Data Engineering | D14: Client | E14: 3 | F14: 3 | G14: =IF(A14="","",IF(AND(E14>=$E$3,F14>=$E$3),"Manage closely",IF(E14>=$E$3,"Keep satisfied",IF(F14>=$E$3,"Keep informed","Monitor")))) -> Monitor | H14: Neutral | I14: Supportive | J14: =IF(OR(A14="",H14="",I14=""),"",IF(I14="Unaware",1,IF(I14="Resistant",2,IF(I14="Neutral",3,IF(I14="Supportive",4,IF(I14="Leading",5,0)))))-IF(H14="Unaware",1,IF(H14="Resistant",2,IF(H14="Neutral",3,IF(H14="Supportive",4,IF(H14="Leading",5,0)))))) -> 1 | K14: =IF(J14="","",J14*E14) -> 3 | L14: Pipeline capacity, data quality rules, ownership of settlement data issues. | M14: Agree data quality acceptance rules and exception ownership; include in sprint reviews for reporting stories. | N14: Tech Lead | O14: Fortnightly | P14: Working session | Q14: D-04, R-05, US-033 | R14: 46266 | S14: Agree pipeline acceptance rules | T14: 46286 | U14: =IF(OR(A14="",T14=""),"",IF(T14<Cover!$C$7,"Overdue","No")) -> No | V14: =IF(G14="Manage closely",ROW(),"") | W14: =IF(G14="Keep satisfied",ROW(),"") | X14: =IF(G14="Keep informed",ROW(),"") | Y14: =IF(G14="Monitor",ROW(),"") -> 14 | Z14: =IF(OR(J14="",N(J14)<=0),"",K14+(1000-ROW())/100000) -> 3.00986
A15: SH-11 | B15: Data Governance Lead | C15: Data Governance | D15: Client | E15: 4 | F15: 2 | G15: =IF(A15="","",IF(AND(E15>=$E$3,F15>=$E$3),"Manage closely",IF(E15>=$E$3,"Keep satisfied",IF(F15>=$E$3,"Keep informed","Monitor")))) -> Keep satisfied | H15: Neutral | I15: Supportive | J15: =IF(OR(A15="",H15="",I15=""),"",IF(I15="Unaware",1,IF(I15="Resistant",2,IF(I15="Neutral",3,IF(I15="Supportive",4,IF(I15="Leading",5,0)))))-IF(H15="Unaware",1,IF(H15="Resistant",2,IF(H15="Neutral",3,IF(H15="Supportive",4,IF(H15="Leading",5,0)))))) -> 1 | K15: =IF(J15="","",J15*E15) -> 4 | L15: Personal data in analytics events; approval workload. | M15: Walk through a privacy-first tracking plan with no personal or card data; ask for conditional approval to unblock pilot metrics. | N15: Product Owner | O15: Monthly | P15: Governance forum | Q15: I-06, CTL-04, KPI-08 | R15: 46273 | S15: Present revised tracking plan for approval | T15: 46296 | U15: =IF(OR(A15="",T15=""),"",IF(T15<Cover!$C$7,"Overdue","No")) -> No | V15: =IF(G15="Manage closely",ROW(),"") | W15: =IF(G15="Keep satisfied",ROW(),"") -> 15 | X15: =IF(G15="Keep informed",ROW(),"") | Y15: =IF(G15="Monitor",ROW(),"") | Z15: =IF(OR(J15="",N(J15)<=0),"",K15+(1000-ROW())/100000) -> 4.00985
A16: SH-12 | B16: Customer Servicing Lead | C16: Customer Servicing | D16: Client | E16: 3 | F16: 3 | G16: =IF(A16="","",IF(AND(E16>=$E$3,F16>=$E$3),"Manage closely",IF(E16>=$E$3,"Keep satisfied",IF(F16>=$E$3,"Keep informed","Monitor")))) -> Monitor | H16: Neutral | I16: Supportive | J16: =IF(OR(A16="",H16="",I16=""),"",IF(I16="Unaware",1,IF(I16="Resistant",2,IF(I16="Neutral",3,IF(I16="Supportive",4,IF(I16="Leading",5,0)))))-IF(H16="Unaware",1,IF(H16="Resistant",2,IF(H16="Neutral",3,IF(H16="Supportive",4,IF(H16="Leading",5,0)))))) -> 1 | K16: =IF(J16="","",J16*E16) -> 3 | L16: Agent training time, call volumes after launch, status API readiness. | M16: Include in readiness huddles from November; share servicing API demo; co-write call scripts. | N16: Product Owner | O16: Monthly | P16: Readiness huddle | Q16: D-06, LR-09, KPI-07 | R16: 46261 | S16: Invite to Sprint 8 review for status API demo | T16: 46321 | U16: =IF(OR(A16="",T16=""),"",IF(T16<Cover!$C$7,"Overdue","No")) -> No | V16: =IF(G16="Manage closely",ROW(),"") | W16: =IF(G16="Keep satisfied",ROW(),"") | X16: =IF(G16="Keep informed",ROW(),"") | Y16: =IF(G16="Monitor",ROW(),"") -> 16 | Z16: =IF(OR(J16="",N(J16)<=0),"",K16+(1000-ROW())/100000) -> 3.00984
A17: SH-13 | B17: Merchant Relationship Lead | C17: Merchant Relationships | D17: Client | E17: 4 | F17: 4 | G17: =IF(A17="","",IF(AND(E17>=$E$3,F17>=$E$3),"Manage closely",IF(E17>=$E$3,"Keep satisfied",IF(F17>=$E$3,"Keep informed","Monitor")))) -> Manage closely | H17: Supportive | I17: Leading | J17: =IF(OR(A17="",H17="",I17=""),"",IF(I17="Unaware",1,IF(I17="Resistant",2,IF(I17="Neutral",3,IF(I17="Supportive",4,IF(I17="Leading",5,0)))))-IF(H17="Unaware",1,IF(H17="Resistant",2,IF(H17="Neutral",3,IF(H17="Supportive",4,IF(H17="Leading",5,0)))))) -> 1 | K17: =IF(J17="","",J17*E17) -> 4 | L17: Merchant pushback on change, pilot recruitment, language needs. | M17: Co-own the GTM plan and pilot recruitment; give RMs an enablement pack and early demo access. | N17: Product Owner | O17: Weekly | P17: Working session | Q17: LR-10, LR-13, CR-04 | R17: 46274 | S17: Finalize pilot merchant list | T17: 46290 | U17: =IF(OR(A17="",T17=""),"",IF(T17<Cover!$C$7,"Overdue","No")) -> No | V17: =IF(G17="Manage closely",ROW(),"") -> 17 | W17: =IF(G17="Keep satisfied",ROW(),"") | X17: =IF(G17="Keep informed",ROW(),"") | Y17: =IF(G17="Monitor",ROW(),"") | Z17: =IF(OR(J17="",N(J17)<=0),"",K17+(1000-ROW())/100000) -> 4.00983
A18: SH-14 | B18: Marketing and Merchant Communications Lead | C18: Marketing | D18: Client | E18: 2 | F18: 3 | G18: =IF(A18="","",IF(AND(E18>=$E$3,F18>=$E$3),"Manage closely",IF(E18>=$E$3,"Keep satisfied",IF(F18>=$E$3,"Keep informed","Monitor")))) -> Monitor | H18: Unaware | I18: Supportive | J18: =IF(OR(A18="",H18="",I18=""),"",IF(I18="Unaware",1,IF(I18="Resistant",2,IF(I18="Neutral",3,IF(I18="Supportive",4,IF(I18="Leading",5,0)))))-IF(H18="Unaware",1,IF(H18="Resistant",2,IF(H18="Neutral",3,IF(H18="Supportive",4,IF(H18="Leading",5,0)))))) -> 3 | K18: =IF(J18="","",J18*E18) -> 6 | L18: Communication lead times, brand approval, channel choice. | M18: Brief on GTM plan and communications calendar; agree approval lead times. | N18: Merchant Relationship Lead | O18: Monthly | P18: Briefing | Q18: LR-11, LR-12 | S18: First briefing on GTM plan | T18: 46300 | U18: =IF(OR(A18="",T18=""),"",IF(T18<Cover!$C$7,"Overdue","No")) -> No | V18: =IF(G18="Manage closely",ROW(),"") | W18: =IF(G18="Keep satisfied",ROW(),"") | X18: =IF(G18="Keep informed",ROW(),"") | Y18: =IF(G18="Monitor",ROW(),"") -> 18 | Z18: =IF(OR(J18="",N(J18)<=0),"",K18+(1000-ROW())/100000) -> 6.00982
A19: SH-15 | B19: Payment Processor Account Manager | C19: Processor (vendor) | D19: Vendor | E19: 4 | F19: 3 | G19: =IF(A19="","",IF(AND(E19>=$E$3,F19>=$E$3),"Manage closely",IF(E19>=$E$3,"Keep satisfied",IF(F19>=$E$3,"Keep informed","Monitor")))) -> Keep satisfied | H19: Neutral | I19: Supportive | J19: =IF(OR(A19="",H19="",I19=""),"",IF(I19="Unaware",1,IF(I19="Resistant",2,IF(I19="Neutral",3,IF(I19="Supportive",4,IF(I19="Leading",5,0)))))-IF(H19="Unaware",1,IF(H19="Resistant",2,IF(H19="Neutral",3,IF(H19="Supportive",4,IF(H19="Leading",5,0)))))) -> 1 | K19: =IF(J19="","",J19*E19) -> 4 | L19: Sandbox stability, production access timelines, integration support effort. | M19: Weekly vendor call with tracked actions; escalate through sponsor if production access slips further. | N19: Project Manager | O19: Weekly | P19: Vendor call | Q19: D-01, I-01, A-02 | R19: 46273 | S19: Escalate sandbox status defect and production access date | T19: 46280 | U19: =IF(OR(A19="",T19=""),"",IF(T19<Cover!$C$7,"Overdue","No")) -> No | V19: =IF(G19="Manage closely",ROW(),"") | W19: =IF(G19="Keep satisfied",ROW(),"") -> 19 | X19: =IF(G19="Keep informed",ROW(),"") | Y19: =IF(G19="Monitor",ROW(),"") | Z19: =IF(OR(J19="",N(J19)<=0),"",K19+(1000-ROW())/100000) -> 4.00981
A20: SH-16 | B20: Document Storage Vendor | C20: Storage vendor | D20: Vendor | E20: 2 | F20: 2 | G20: =IF(A20="","",IF(AND(E20>=$E$3,F20>=$E$3),"Manage closely",IF(E20>=$E$3,"Keep satisfied",IF(F20>=$E$3,"Keep informed","Monitor")))) -> Monitor | H20: Neutral | I20: Neutral | J20: =IF(OR(A20="",H20="",I20=""),"",IF(I20="Unaware",1,IF(I20="Resistant",2,IF(I20="Neutral",3,IF(I20="Supportive",4,IF(I20="Leading",5,0)))))-IF(H20="Unaware",1,IF(H20="Resistant",2,IF(H20="Neutral",3,IF(H20="Supportive",4,IF(H20="Leading",5,0)))))) -> 0 | K20: =IF(J20="","",J20*E20) -> 0 | L20: Completing the third-party risk assessment. | M20: Send questionnaire and SOC 2 request early; monitor only. | N20: Tech Lead | O20: As needed | P20: Email | Q20: R-08 | R20: 46268 | S20: Chase security questionnaire | T20: 46274 | U20: =IF(OR(A20="",T20=""),"",IF(T20<Cover!$C$7,"Overdue","No")) -> Overdue | V20: =IF(G20="Manage closely",ROW(),"") | W20: =IF(G20="Keep satisfied",ROW(),"") | X20: =IF(G20="Keep informed",ROW(),"") | Y20: =IF(G20="Monitor",ROW(),"") -> 20 | Z20: =IF(OR(J20="",N(J20)<=0),"",K20+(1000-ROW())/100000)
A21: SH-17 | B21: Pilot merchants (10) | C21: Merchants | D21: External | E21: 2 | F21: 5 | G21: =IF(A21="","",IF(AND(E21>=$E$3,F21>=$E$3),"Manage closely",IF(E21>=$E$3,"Keep satisfied",IF(F21>=$E$3,"Keep informed","Monitor")))) -> Keep informed | H21: Unaware | I21: Supportive | J21: =IF(OR(A21="",H21="",I21=""),"",IF(I21="Unaware",1,IF(I21="Resistant",2,IF(I21="Neutral",3,IF(I21="Supportive",4,IF(I21="Leading",5,0)))))-IF(H21="Unaware",1,IF(H21="Resistant",2,IF(H21="Neutral",3,IF(H21="Supportive",4,IF(H21="Leading",5,0)))))) -> 3 | K21: =IF(J21="","",J21*E21) -> 6 | L21: Ease of use, time saved, confidence their deadlines are safe. | M21: White-glove onboarding, weekly feedback calls during pilot, visible changes made from their feedback. | N21: Merchant Relationship Lead | O21: Weekly during pilot | P21: Onboarding and feedback calls | Q21: A-01, R-04, KPI-08 | S21: Send pilot invitations once terms are approved | T21: 46328 | U21: =IF(OR(A21="",T21=""),"",IF(T21<Cover!$C$7,"Overdue","No")) -> No | V21: =IF(G21="Manage closely",ROW(),"") | W21: =IF(G21="Keep satisfied",ROW(),"") | X21: =IF(G21="Keep informed",ROW(),"") -> 21 | Y21: =IF(G21="Monitor",ROW(),"") | Z21: =IF(OR(J21="",N(J21)<=0),"",K21+(1000-ROW())/100000) -> 6.00979
A22: SH-18 | B22: Delivery squads (Portal, Integration, Data) | C22: Delivery team | D22: Delivery partner | E22: 3 | F22: 5 | G22: =IF(A22="","",IF(AND(E22>=$E$3,F22>=$E$3),"Manage closely",IF(E22>=$E$3,"Keep satisfied",IF(F22>=$E$3,"Keep informed","Monitor")))) -> Keep informed | H22: Supportive | I22: Supportive | J22: =IF(OR(A22="",H22="",I22=""),"",IF(I22="Unaware",1,IF(I22="Resistant",2,IF(I22="Neutral",3,IF(I22="Supportive",4,IF(I22="Leading",5,0)))))-IF(H22="Unaware",1,IF(H22="Resistant",2,IF(H22="Neutral",3,IF(H22="Supportive",4,IF(H22="Leading",5,0)))))) -> 0 | K22: =IF(J22="","",J22*E22) -> 0 | L22: Clear priorities, fast unblocking, stable scope. | M22: Sprint ceremonies; blockers raised daily and tracked in RAID; explain every scope change and why. | N22: Product Owner | O22: Daily | P22: Stand-up and sprint ceremonies | Q22: I-01, R-07 | R22: 46275 | S22: Sprint 4 review and retrospective | T22: 46276 | U22: =IF(OR(A22="",T22=""),"",IF(T22<Cover!$C$7,"Overdue","No")) -> No | V22: =IF(G22="Manage closely",ROW(),"") | W22: =IF(G22="Keep satisfied",ROW(),"") | X22: =IF(G22="Keep informed",ROW(),"") -> 22 | Y22: =IF(G22="Monitor",ROW(),"") | Z22: =IF(OR(J22="",N(J22)<=0),"",K22+(1000-ROW())/100000)
G23: =IF(A23="","",IF(AND(E23>=$E$3,F23>=$E$3),"Manage closely",IF(E23>=$E$3,"Keep satisfied",IF(F23>=$E$3,"Keep informed","Monitor")))) | J23: =IF(OR(A23="",H23="",I23=""),"",IF(I23="Unaware",1,IF(I23="Resistant",2,IF(I23="Neutral",3,IF(I23="Supportive",4,IF(I23="Leading",5,0)))))-IF(H23="Unaware",1,IF(H23="Resistant",2,IF(H23="Neutral",3,IF(H23="Supportive",4,IF(H23="Leading",5,0)))))) | K23: =IF(J23="","",J23*E23) | U23: =IF(OR(A23="",T23=""),"",IF(T23<Cover!$C$7,"Overdue","No")) | V23: =IF(G23="Manage closely",ROW(),"") | W23: =IF(G23="Keep satisfied",ROW(),"") | X23: =IF(G23="Keep informed",ROW(),"") | Y23: =IF(G23="Monitor",ROW(),"") | Z23: =IF(OR(J23="",N(J23)<=0),"",K23+(1000-ROW())/100000)
G24: =IF(A24="","",IF(AND(E24>=$E$3,F24>=$E$3),"Manage closely",IF(E24>=$E$3,"Keep satisfied",IF(F24>=$E$3,"Keep informed","Monitor")))) | J24: =IF(OR(A24="",H24="",I24=""),"",IF(I24="Unaware",1,IF(I24="Resistant",2,IF(I24="Neutral",3,IF(I24="Supportive",4,IF(I24="Leading",5,0)))))-IF(H24="Unaware",1,IF(H24="Resistant",2,IF(H24="Neutral",3,IF(H24="Supportive",4,IF(H24="Leading",5,0)))))) | K24: =IF(J24="","",J24*E24) | U24: =IF(OR(A24="",T24=""),"",IF(T24<Cover!$C$7,"Overdue","No")) | V24: =IF(G24="Manage closely",ROW(),"") | W24: =IF(G24="Keep satisfied",ROW(),"") | X24: =IF(G24="Keep informed",ROW(),"") | Y24: =IF(G24="Monitor",ROW(),"") | Z24: =IF(OR(J24="",N(J24)<=0),"",K24+(1000-ROW())/100000)
G25: =IF(A25="","",IF(AND(E25>=$E$3,F25>=$E$3),"Manage closely",IF(E25>=$E$3,"Keep satisfied",IF(F25>=$E$3,"Keep informed","Monitor")))) | J25: =IF(OR(A25="",H25="",I25=""),"",IF(I25="Unaware",1,IF(I25="Resistant",2,IF(I25="Neutral",3,IF(I25="Supportive",4,IF(I25="Leading",5,0)))))-IF(H25="Unaware",1,IF(H25="Resistant",2,IF(H25="Neutral",3,IF(H25="Supportive",4,IF(H25="Leading",5,0)))))) | K25: =IF(J25="","",J25*E25) | U25: =IF(OR(A25="",T25=""),"",IF(T25<Cover!$C$7,"Overdue","No")) | V25: =IF(G25="Manage closely",ROW(),"") | W25: =IF(G25="Keep satisfied",ROW(),"") | X25: =IF(G25="Keep informed",ROW(),"") | Y25: =IF(G25="Monitor",ROW(),"") | Z25: =IF(OR(J25="",N(J25)<=0),"",K25+(1000-ROW())/100000)
G26: =IF(A26="","",IF(AND(E26>=$E$3,F26>=$E$3),"Manage closely",IF(E26>=$E$3,"Keep satisfied",IF(F26>=$E$3,"Keep informed","Monitor")))) | J26: =IF(OR(A26="",H26="",I26=""),"",IF(I26="Unaware",1,IF(I26="Resistant",2,IF(I26="Neutral",3,IF(I26="Supportive",4,IF(I26="Leading",5,0)))))-IF(H26="Unaware",1,IF(H26="Resistant",2,IF(H26="Neutral",3,IF(H26="Supportive",4,IF(H26="Leading",5,0)))))) | K26: =IF(J26="","",J26*E26) | U26: =IF(OR(A26="",T26=""),"",IF(T26<Cover!$C$7,"Overdue","No")) | V26: =IF(G26="Manage closely",ROW(),"") | W26: =IF(G26="Keep satisfied",ROW(),"") | X26: =IF(G26="Keep informed",ROW(),"") | Y26: =IF(G26="Monitor",ROW(),"") | Z26: =IF(OR(J26="",N(J26)<=0),"",K26+(1000-ROW())/100000)
G27: =IF(A27="","",IF(AND(E27>=$E$3,F27>=$E$3),"Manage closely",IF(E27>=$E$3,"Keep satisfied",IF(F27>=$E$3,"Keep informed","Monitor")))) | J27: =IF(OR(A27="",H27="",I27=""),"",IF(I27="Unaware",1,IF(I27="Resistant",2,IF(I27="Neutral",3,IF(I27="Supportive",4,IF(I27="Leading",5,0)))))-IF(H27="Unaware",1,IF(H27="Resistant",2,IF(H27="Neutral",3,IF(H27="Supportive",4,IF(H27="Leading",5,0)))))) | K27: =IF(J27="","",J27*E27) | U27: =IF(OR(A27="",T27=""),"",IF(T27<Cover!$C$7,"Overdue","No")) | V27: =IF(G27="Manage closely",ROW(),"") | W27: =IF(G27="Keep satisfied",ROW(),"") | X27: =IF(G27="Keep informed",ROW(),"") | Y27: =IF(G27="Monitor",ROW(),"") | Z27: =IF(OR(J27="",N(J27)<=0),"",K27+(1000-ROW())/100000)
G28: =IF(A28="","",IF(AND(E28>=$E$3,F28>=$E$3),"Manage closely",IF(E28>=$E$3,"Keep satisfied",IF(F28>=$E$3,"Keep informed","Monitor")))) | J28: =IF(OR(A28="",H28="",I28=""),"",IF(I28="Unaware",1,IF(I28="Resistant",2,IF(I28="Neutral",3,IF(I28="Supportive",4,IF(I28="Leading",5,0)))))-IF(H28="Unaware",1,IF(H28="Resistant",2,IF(H28="Neutral",3,IF(H28="Supportive",4,IF(H28="Leading",5,0)))))) | K28: =IF(J28="","",J28*E28) | U28: =IF(OR(A28="",T28=""),"",IF(T28<Cover!$C$7,"Overdue","No")) | V28: =IF(G28="Manage closely",ROW(),"") | W28: =IF(G28="Keep satisfied",ROW(),"") | X28: =IF(G28="Keep informed",ROW(),"") | Y28: =IF(G28="Monitor",ROW(),"") | Z28: =IF(OR(J28="",N(J28)<=0),"",K28+(1000-ROW())/100000)
G29: =IF(A29="","",IF(AND(E29>=$E$3,F29>=$E$3),"Manage closely",IF(E29>=$E$3,"Keep satisfied",IF(F29>=$E$3,"Keep informed","Monitor")))) | J29: =IF(OR(A29="",H29="",I29=""),"",IF(I29="Unaware",1,IF(I29="Resistant",2,IF(I29="Neutral",3,IF(I29="Supportive",4,IF(I29="Leading",5,0)))))-IF(H29="Unaware",1,IF(H29="Resistant",2,IF(H29="Neutral",3,IF(H29="Supportive",4,IF(H29="Leading",5,0)))))) | K29: =IF(J29="","",J29*E29) | U29: =IF(OR(A29="",T29=""),"",IF(T29<Cover!$C$7,"Overdue","No")) | V29: =IF(G29="Manage closely",ROW(),"") | W29: =IF(G29="Keep satisfied",ROW(),"") | X29: =IF(G29="Keep informed",ROW(),"") | Y29: =IF(G29="Monitor",ROW(),"") | Z29: =IF(OR(J29="",N(J29)<=0),"",K29+(1000-ROW())/100000)
G30: =IF(A30="","",IF(AND(E30>=$E$3,F30>=$E$3),"Manage closely",IF(E30>=$E$3,"Keep satisfied",IF(F30>=$E$3,"Keep informed","Monitor")))) | J30: =IF(OR(A30="",H30="",I30=""),"",IF(I30="Unaware",1,IF(I30="Resistant",2,IF(I30="Neutral",3,IF(I30="Supportive",4,IF(I30="Leading",5,0)))))-IF(H30="Unaware",1,IF(H30="Resistant",2,IF(H30="Neutral",3,IF(H30="Supportive",4,IF(H30="Leading",5,0)))))) | K30: =IF(J30="","",J30*E30) | U30: =IF(OR(A30="",T30=""),"",IF(T30<Cover!$C$7,"Overdue","No")) | V30: =IF(G30="Manage closely",ROW(),"") | W30: =IF(G30="Keep satisfied",ROW(),"") | X30: =IF(G30="Keep informed",ROW(),"") | Y30: =IF(G30="Monitor",ROW(),"") | Z30: =IF(OR(J30="",N(J30)<=0),"",K30+(1000-ROW())/100000)
G31: =IF(A31="","",IF(AND(E31>=$E$3,F31>=$E$3),"Manage closely",IF(E31>=$E$3,"Keep satisfied",IF(F31>=$E$3,"Keep informed","Monitor")))) | J31: =IF(OR(A31="",H31="",I31=""),"",IF(I31="Unaware",1,IF(I31="Resistant",2,IF(I31="Neutral",3,IF(I31="Supportive",4,IF(I31="Leading",5,0)))))-IF(H31="Unaware",1,IF(H31="Resistant",2,IF(H31="Neutral",3,IF(H31="Supportive",4,IF(H31="Leading",5,0)))))) | K31: =IF(J31="","",J31*E31) | U31: =IF(OR(A31="",T31=""),"",IF(T31<Cover!$C$7,"Overdue","No")) | V31: =IF(G31="Manage closely",ROW(),"") | W31: =IF(G31="Keep satisfied",ROW(),"") | X31: =IF(G31="Keep informed",ROW(),"") | Y31: =IF(G31="Monitor",ROW(),"") | Z31: =IF(OR(J31="",N(J31)<=0),"",K31+(1000-ROW())/100000)
G32: =IF(A32="","",IF(AND(E32>=$E$3,F32>=$E$3),"Manage closely",IF(E32>=$E$3,"Keep satisfied",IF(F32>=$E$3,"Keep informed","Monitor")))) | J32: =IF(OR(A32="",H32="",I32=""),"",IF(I32="Unaware",1,IF(I32="Resistant",2,IF(I32="Neutral",3,IF(I32="Supportive",4,IF(I32="Leading",5,0)))))-IF(H32="Unaware",1,IF(H32="Resistant",2,IF(H32="Neutral",3,IF(H32="Supportive",4,IF(H32="Leading",5,0)))))) | K32: =IF(J32="","",J32*E32) | U32: =IF(OR(A32="",T32=""),"",IF(T32<Cover!$C$7,"Overdue","No")) | V32: =IF(G32="Manage closely",ROW(),"") | W32: =IF(G32="Keep satisfied",ROW(),"") | X32: =IF(G32="Keep informed",ROW(),"") | Y32: =IF(G32="Monitor",ROW(),"") | Z32: =IF(OR(J32="",N(J32)<=0),"",K32+(1000-ROW())/100000)
G33: =IF(A33="","",IF(AND(E33>=$E$3,F33>=$E$3),"Manage closely",IF(E33>=$E$3,"Keep satisfied",IF(F33>=$E$3,"Keep informed","Monitor")))) | J33: =IF(OR(A33="",H33="",I33=""),"",IF(I33="Unaware",1,IF(I33="Resistant",2,IF(I33="Neutral",3,IF(I33="Supportive",4,IF(I33="Leading",5,0)))))-IF(H33="Unaware",1,IF(H33="Resistant",2,IF(H33="Neutral",3,IF(H33="Supportive",4,IF(H33="Leading",5,0)))))) | K33: =IF(J33="","",J33*E33) | U33: =IF(OR(A33="",T33=""),"",IF(T33<Cover!$C$7,"Overdue","No")) | V33: =IF(G33="Manage closely",ROW(),"") | W33: =IF(G33="Keep satisfied",ROW(),"") | X33: =IF(G33="Keep informed",ROW(),"") | Y33: =IF(G33="Monitor",ROW(),"") | Z33: =IF(OR(J33="",N(J33)<=0),"",K33+(1000-ROW())/100000)
G34: =IF(A34="","",IF(AND(E34>=$E$3,F34>=$E$3),"Manage closely",IF(E34>=$E$3,"Keep satisfied",IF(F34>=$E$3,"Keep informed","Monitor")))) | J34: =IF(OR(A34="",H34="",I34=""),"",IF(I34="Unaware",1,IF(I34="Resistant",2,IF(I34="Neutral",3,IF(I34="Supportive",4,IF(I34="Leading",5,0)))))-IF(H34="Unaware",1,IF(H34="Resistant",2,IF(H34="Neutral",3,IF(H34="Supportive",4,IF(H34="Leading",5,0)))))) | K34: =IF(J34="","",J34*E34) | U34: =IF(OR(A34="",T34=""),"",IF(T34<Cover!$C$7,"Overdue","No")) | V34: =IF(G34="Manage closely",ROW(),"") | W34: =IF(G34="Keep satisfied",ROW(),"") | X34: =IF(G34="Keep informed",ROW(),"") | Y34: =IF(G34="Monitor",ROW(),"") | Z34: =IF(OR(J34="",N(J34)<=0),"",K34+(1000-ROW())/100000)
... G54: =IF(A54="","",IF(AND(E54>=$E$3,F54>=$E$3),"Manage closely",IF(E54>=$E$3,"Keep satisfied",IF(F54>=$E$3,"Keep informed","Monitor")))) | J54: =IF(OR(A54="",H54="",I54=""),"",IF(I54="Unaware",1,IF(I54="Resistant",2,IF(I54="Neutral",3,IF(I54="Supportive",4,IF(I54="Leading",5,0)))))-IF(H54="Unaware",1,IF(H54="Resistant",2,IF(H54="Neutral",3,IF(H54="Supportive",4,IF(H54="Leading",5,0)))))) | K54: =IF(J54="","",J54*E54) | U54: =IF(OR(A54="",T54=""),"",IF(T54<Cover!$C$7,"Overdue","No")) | V54: =IF(G54="Manage closely",ROW(),"") | W54: =IF(G54="Keep satisfied",ROW(),"") | X54: =IF(G54="Keep informed",ROW(),"") | Y54: =IF(G54="Monitor",ROW(),"") | Z54: =IF(OR(J54="",N(J54)<=0),"",K54+(1000-ROW())/100000)

Sheet RACI Matrix
A1: RACI Matrix
A2: Merchant Payment Operations & Dispute Hub · Simulation project · Decision rights align with Change Log thresholds
A3: Use R, A, C, I or R/A. Each activity needs exactly one A and at least one R; the Check column flags problems.
A4: ID | B4: Activity or decision | C4: Area | D4: Business Sponsor | E4: Steering Committee | F4: Engagement Lead | G4: Product Owner | H4: Project Manager | I4: Tech Lead | J4: Dispute Ops Lead | K4: Finance Lead | L4: Compliance Lead | M4: InfoSec Lead | N4: Legal Counsel | O4: Data Governance Lead | P4: Merchant Relationship Lead | Q4: Servicing Lead | R4: A count | S4: R count | T4: Check
A5: RA-01 | B5: Approve MVP scope baseline | C5: Scope | D5: A | E5: I | F5: C | G5: R | H5: C | I5: C | J5: C | K5: C | L5: C | P5: C | R5: =IF(A5="","",COUNTIF(D5:Q5,"*A*")) -> 1 | S5: =IF(A5="","",COUNTIF(D5:Q5,"*R*")) -> 1 | T5: =IF(A5="","",IF(R5<>1,"Needs one A",IF(S5<1,"Needs an R","OK"))) -> OK
A6: RA-02 | B6: Prioritize and order the product backlog | C6: Scope | D6: C | G6: R/A | H6: I | I6: C | J6: C | R6: =IF(A6="","",COUNTIF(D6:Q6,"*A*")) -> 1 | S6: =IF(A6="","",COUNTIF(D6:Q6,"*R*")) -> 1 | T6: =IF(A6="","",IF(R6<>1,"Needs one A",IF(S6<1,"Needs an R","OK"))) -> OK
A7: RA-03 | B7: Approve Low-impact change requests | C7: Change control | D7: I | G7: R/A | H7: I | I7: C | R7: =IF(A7="","",COUNTIF(D7:Q7,"*A*")) -> 1 | S7: =IF(A7="","",COUNTIF(D7:Q7,"*R*")) -> 1 | T7: =IF(A7="","",IF(R7<>1,"Needs one A",IF(S7<1,"Needs an R","OK"))) -> OK
A8: RA-04 | B8: Approve Medium-impact change requests | C8: Change control | D8: A | E8: I | G8: R | H8: C | I8: C | K8: C | R8: =IF(A8="","",COUNTIF(D8:Q8,"*A*")) -> 1 | S8: =IF(A8="","",COUNTIF(D8:Q8,"*R*")) -> 1 | T8: =IF(A8="","",IF(R8<>1,"Needs one A",IF(S8<1,"Needs an R","OK"))) -> OK
A9: RA-05 | B9: Approve High-impact and compliance change requests | C9: Change control | D9: C | E9: A | F9: C | G9: R | H9: C | I9: C | K9: C | L9: C | R9: =IF(A9="","",COUNTIF(D9:Q9,"*A*")) -> 1 | S9: =IF(A9="","",COUNTIF(D9:Q9,"*R*")) -> 1 | T9: =IF(A9="","",IF(R9<>1,"Needs one A",IF(S9<1,"Needs an R","OK"))) -> OK
A10: RA-06 | B10: Maintain RAID log and escalate risks | C10: Governance | D10: I | E10: I | F10: C | G10: R | H10: A | I10: R | R10: =IF(A10="","",COUNTIF(D10:Q10,"*A*")) -> 1 | S10: =IF(A10="","",COUNTIF(D10:Q10,"*R*")) -> 2 | T10: =IF(A10="","",IF(R10<>1,"Needs one A",IF(S10<1,"Needs an R","OK"))) -> OK
A11: RA-07 | B11: Approve compliance controls and evidence | C11: Compliance | G11: R | I11: R | L11: A | M11: C | N11: C | O11: C | R11: =IF(A11="","",COUNTIF(D11:Q11,"*A*")) -> 1 | S11: =IF(A11="","",COUNTIF(D11:Q11,"*R*")) -> 2 | T11: =IF(A11="","",IF(R11<>1,"Needs one A",IF(S11<1,"Needs an R","OK"))) -> OK
A12: RA-08 | B12: Security sign-off for go-live | C12: Compliance | E12: I | G12: I | H12: I | I12: R | L12: C | M12: A | R12: =IF(A12="","",COUNTIF(D12:Q12,"*A*")) -> 1 | S12: =IF(A12="","",COUNTIF(D12:Q12,"*R*")) -> 1 | T12: =IF(A12="","",IF(R12<>1,"Needs one A",IF(S12<1,"Needs an R","OK"))) -> OK
A13: RA-09 | B13: Approve analytics tracking plan | C13: Data | G13: R | I13: C | L13: C | O13: A | R13: =IF(A13="","",COUNTIF(D13:Q13,"*A*")) -> 1 | S13: =IF(A13="","",COUNTIF(D13:Q13,"*R*")) -> 1 | T13: =IF(A13="","",IF(R13<>1,"Needs one A",IF(S13<1,"Needs an R","OK"))) -> OK
A14: RA-10 | B14: Approve KPI and dispute outcome definitions | C14: Data | D14: A | E14: I | G14: R | J14: C | K14: C | O14: C | R14: =IF(A14="","",COUNTIF(D14:Q14,"*A*")) -> 1 | S14: =IF(A14="","",COUNTIF(D14:Q14,"*R*")) -> 1 | T14: =IF(A14="","",IF(R14<>1,"Needs one A",IF(S14<1,"Needs an R","OK"))) -> OK
A15: RA-11 | B15: Execute user acceptance testing | C15: Quality | G15: A | H15: C | I15: C | J15: R | K15: R | Q15: C | R15: =IF(A15="","",COUNTIF(D15:Q15,"*A*")) -> 1 | S15: =IF(A15="","",COUNTIF(D15:Q15,"*R*")) -> 2 | T15: =IF(A15="","",IF(R15<>1,"Needs one A",IF(S15<1,"Needs an R","OK"))) -> OK
A16: RA-12 | B16: Sign off user acceptance testing | C16: Quality | D16: A | G16: R | H16: I | J16: R | K16: R | L16: C | R16: =IF(A16="","",COUNTIF(D16:Q16,"*A*")) -> 1 | S16: =IF(A16="","",COUNTIF(D16:Q16,"*R*")) -> 3 | T16: =IF(A16="","",IF(R16<>1,"Needs one A",IF(S16<1,"Needs an R","OK"))) -> OK
A17: RA-13 | B17: Go-live and pilot go / no-go decision | C17: Launch | D17: R | E17: A | F17: C | G17: R | H17: R | I17: C | J17: C | L17: C | M17: C | P17: C | R17: =IF(A17="","",COUNTIF(D17:Q17,"*A*")) -> 1 | S17: =IF(A17="","",COUNTIF(D17:Q17,"*R*")) -> 3 | T17: =IF(A17="","",IF(R17<>1,"Needs one A",IF(S17<1,"Needs an R","OK"))) -> OK
A18: RA-14 | B18: Merchant communications and pilot recruitment | C18: Launch | D18: I | G18: C | L18: C | N18: C | P18: R/A | R18: =IF(A18="","",COUNTIF(D18:Q18,"*A*")) -> 1 | S18: =IF(A18="","",COUNTIF(D18:Q18,"*R*")) -> 1 | T18: =IF(A18="","",IF(R18<>1,"Needs one A",IF(S18<1,"Needs an R","OK"))) -> OK
A19: RA-15 | B19: Servicing readiness and agent training | C19: Launch | G19: C | H19: I | J19: C | Q19: R/A | R19: =IF(A19="","",COUNTIF(D19:Q19,"*A*")) -> 1 | S19: =IF(A19="","",COUNTIF(D19:Q19,"*R*")) -> 1 | T19: =IF(A19="","",IF(R19<>1,"Needs one A",IF(S19<1,"Needs an R","OK"))) -> OK
A20: RA-16 | B20: Business case and benefits tracking | C20: Value | D20: A | E20: I | F20: C | G20: R | J20: C | K20: C | R20: =IF(A20="","",COUNTIF(D20:Q20,"*A*")) -> 1 | S20: =IF(A20="","",COUNTIF(D20:Q20,"*R*")) -> 1 | T20: =IF(A20="","",IF(R20<>1,"Needs one A",IF(S20<1,"Needs an R","OK"))) -> OK
A21: RA-17 | B21: Weekly status reporting | C21: Governance | D21: I | E21: I | F21: C | G21: C | H21: R/A | R21: =IF(A21="","",COUNTIF(D21:Q21,"*A*")) -> 1 | S21: =IF(A21="","",COUNTIF(D21:Q21,"*R*")) -> 1 | T21: =IF(A21="","",IF(R21<>1,"Needs one A",IF(S21<1,"Needs an R","OK"))) -> OK
A22: RA-18 | B22: Vendor and third-party escalations | C22: Governance | D22: A | F22: C | G22: I | H22: R | I22: R | R22: =IF(A22="","",COUNTIF(D22:Q22,"*A*")) -> 1 | S22: =IF(A22="","",COUNTIF(D22:Q22,"*R*")) -> 2 | T22: =IF(A22="","",IF(R22<>1,"Needs one A",IF(S22<1,"Needs an R","OK"))) -> OK
R23: =IF(A23="","",COUNTIF(D23:Q23,"*A*")) | S23: =IF(A23="","",COUNTIF(D23:Q23,"*R*")) | T23: =IF(A23="","",IF(R23<>1,"Needs one A",IF(S23<1,"Needs an R","OK")))
B24: Accountable for (count) | D24: =COUNTIF(D5:D40,"*A*") -> 6 | E24: =COUNTIF(E5:E40,"*A*") -> 2 | F24: =COUNTIF(F5:F40,"*A*") -> 0 | G24: =COUNTIF(G5:G40,"*A*") -> 3 | H24: =COUNTIF(H5:H40,"*A*") -> 2 | I24: =COUNTIF(I5:I40,"*A*") -> 0 | J24: =COUNTIF(J5:J40,"*A*") -> 0 | K24: =COUNTIF(K5:K40,"*A*") -> 0 | ... Q24: =COUNTIF(Q5:Q40,"*A*") -> 1 | R24: =IF(A24="","",COUNTIF(D24:Q24,"*A*")) | S24: =IF(A24="","",COUNTIF(D24:Q24,"*R*")) | T24: =IF(A24="","",IF(R24<>1,"Needs one A",IF(S24<1,"Needs an R","OK")))
B25: Responsible for (count) | D25: =COUNTIF(D5:D40,"*R*") -> 3 | E25: =COUNTIF(E5:E40,"*R*") -> 2 | F25: =COUNTIF(F5:F40,"*R*") -> 2 | G25: =COUNTIF(G5:G40,"*R*") -> 14 | H25: =COUNTIF(H5:H40,"*R*") -> 5 | I25: =COUNTIF(I5:I40,"*R*") -> 6 | J25: =COUNTIF(J5:J40,"*R*") -> 4 | K25: =COUNTIF(K5:K40,"*R*") -> 4 | ... Q25: =COUNTIF(Q5:Q40,"*R*") -> 3 | R25: =IF(A25="","",COUNTIF(D25:Q25,"*A*")) | S25: =IF(A25="","",COUNTIF(D25:Q25,"*R*")) | T25: =IF(A25="","",IF(R25<>1,"Needs one A",IF(S25<1,"Needs an R","OK")))
B26: Role load helps spot overload: a role accountable for many decisions may slow the engagement down. | R26: =IF(A26="","",COUNTIF(D26:Q26,"*A*")) | S26: =IF(A26="","",COUNTIF(D26:Q26,"*R*")) | T26: =IF(A26="","",IF(R26<>1,"Needs one A",IF(S26<1,"Needs an R","OK")))
R27: =IF(A27="","",COUNTIF(D27:Q27,"*A*")) | S27: =IF(A27="","",COUNTIF(D27:Q27,"*R*")) | T27: =IF(A27="","",IF(R27<>1,"Needs one A",IF(S27<1,"Needs an R","OK")))
R28: =IF(A28="","",COUNTIF(D28:Q28,"*A*")) | S28: =IF(A28="","",COUNTIF(D28:Q28,"*R*")) | T28: =IF(A28="","",IF(R28<>1,"Needs one A",IF(S28<1,"Needs an R","OK")))
R29: =IF(A29="","",COUNTIF(D29:Q29,"*A*")) | S29: =IF(A29="","",COUNTIF(D29:Q29,"*R*")) | T29: =IF(A29="","",IF(R29<>1,"Needs one A",IF(S29<1,"Needs an R","OK")))
R30: =IF(A30="","",COUNTIF(D30:Q30,"*A*")) | S30: =IF(A30="","",COUNTIF(D30:Q30,"*R*")) | T30: =IF(A30="","",IF(R30<>1,"Needs one A",IF(S30<1,"Needs an R","OK")))
R31: =IF(A31="","",COUNTIF(D31:Q31,"*A*")) | S31: =IF(A31="","",COUNTIF(D31:Q31,"*R*")) | T31: =IF(A31="","",IF(R31<>1,"Needs one A",IF(S31<1,"Needs an R","OK")))
R32: =IF(A32="","",COUNTIF(D32:Q32,"*A*")) | S32: =IF(A32="","",COUNTIF(D32:Q32,"*R*")) | T32: =IF(A32="","",IF(R32<>1,"Needs one A",IF(S32<1,"Needs an R","OK")))
R33: =IF(A33="","",COUNTIF(D33:Q33,"*A*")) | S33: =IF(A33="","",COUNTIF(D33:Q33,"*R*")) | T33: =IF(A33="","",IF(R33<>1,"Needs one A",IF(S33<1,"Needs an R","OK")))
R34: =IF(A34="","",COUNTIF(D34:Q34,"*A*")) | S34: =IF(A34="","",COUNTIF(D34:Q34,"*R*")) | T34: =IF(A34="","",IF(R34<>1,"Needs one A",IF(S34<1,"Needs an R","OK")))
R35: =IF(A35="","",COUNTIF(D35:Q35,"*A*")) | S35: =IF(A35="","",COUNTIF(D35:Q35,"*R*")) | T35: =IF(A35="","",IF(R35<>1,"Needs one A",IF(S35<1,"Needs an R","OK")))
R36: =IF(A36="","",COUNTIF(D36:Q36,"*A*")) | S36: =IF(A36="","",COUNTIF(D36:Q36,"*R*")) | T36: =IF(A36="","",IF(R36<>1,"Needs one A",IF(S36<1,"Needs an R","OK")))
R37: =IF(A37="","",COUNTIF(D37:Q37,"*A*")) | S37: =IF(A37="","",COUNTIF(D37:Q37,"*R*")) | T37: =IF(A37="","",IF(R37<>1,"Needs one A",IF(S37<1,"Needs an R","OK")))
R38: =IF(A38="","",COUNTIF(D38:Q38,"*A*")) | S38: =IF(A38="","",COUNTIF(D38:Q38,"*R*")) | T38: =IF(A38="","",IF(R38<>1,"Needs one A",IF(S38<1,"Needs an R","OK")))
... R40: =IF(A40="","",COUNTIF(D40:Q40,"*A*")) | S40: =IF(A40="","",COUNTIF(D40:Q40,"*R*")) | T40: =IF(A40="","",IF(R40<>1,"Needs one A",IF(S40<1,"Needs an R","OK")))

Sheet Governance
A1: Governance & Escalation
A2: Merchant Payment Operations & Dispute Hub · Simulation project · Decision forums, cadence and escalation path
A3: Update Next date after each meeting. Grey column shows days until the next meeting from the reporting date.
A4: Forum | B4: Purpose | C4: Chair | D4: Attendees | E4: Frequency | F4: Day and time | G4: Inputs | H4: Decisions and outputs | I4: Next date | J4: Days until | K4: h_next
A5: Steering Committee | B5: Make High-impact decisions; track delivery confidence, budget and compliance risk. | C5: Business Sponsor | D5: Steering Committee delegates, Engagement Lead, Product Owner, Project Manager | E5: Fortnightly | F5: Thursday 16:00 | G5: Decision papers, RAID top risks, change log, business case | H5: Approve High-impact changes, go / no-go decisions, escalations | I5: 46289 | J5: =IF(I5="","",I5-Cover!$C$7) -> 14 | K5: =IF(AND(I5<>"",N(J5)>=0,N(J5)<=14),I5+ROW()/100000,"") -> 46289
A6: Sponsor 1:1 | B6: Pre-wire decisions and keep the sponsor ahead of issues. | C6: Engagement Lead | D6: Business Sponsor, Product Owner | E6: Weekly | F6: Monday 09:30 | G6: Upcoming decisions, stakeholder issues | H6: Medium-impact change decisions; escalation support | I6: 46279 | J6: =IF(I6="","",I6-Cover!$C$7) -> 4 | K6: =IF(AND(I6<>"",N(J6)>=0,N(J6)<=14),I6+ROW()/100000,"") -> 46279
A7: Weekly status and RAID / change review | B7: Review progress, RAID items and pending change requests. | C7: Project Manager | D7: Product Owner, Tech Lead, workstream leads | E7: Weekly | F7: Wednesday 11:00 | G7: Status report, RAID log, change log | H7: Owners and dates for actions; items to escalate | I7: 46281 | J7: =IF(I7="","",I7-Cover!$C$7) -> 6 | K7: =IF(AND(I7<>"",N(J7)>=0,N(J7)<=14),I7+ROW()/100000,"") -> 46281
A8: Sprint review | B8: Demo the increment and gather stakeholder feedback. | C8: Product Owner | D8: Delivery squads, Dispute Ops Lead, Finance Lead, interested stakeholders | E8: Every 2 weeks | F8: Friday 14:00 (sprint end) | G8: Done stories, sprint goal | H8: Accepted stories; backlog changes | I8: 46276 | J8: =IF(I8="","",I8-Cover!$C$7) -> 1 | K8: =IF(AND(I8<>"",N(J8)>=0,N(J8)<=14),I8+ROW()/100000,"") -> 46276
A9: Sprint planning | B9: Agree sprint goal and commitment. | C9: Product Owner | D9: Delivery squads, Tech Lead | E9: Every 2 weeks | F9: Monday 10:00 (sprint start) | G9: Ready backlog items, capacity | H9: Sprint goal and committed items | I9: 46279 | J9: =IF(I9="","",I9-Cover!$C$7) -> 4 | K9: =IF(AND(I9<>"",N(J9)>=0,N(J9)<=14),I9+ROW()/100000,"") -> 46279
A10: Backlog refinement | B10: Keep the next two sprints Ready. | C10: Product Owner | D10: Tech Lead, BA, squad representatives, SMEs as needed | E10: Weekly | F10: Tuesday 14:00 | G10: Upcoming stories, designs, dependencies | H10: Refined and estimated stories | I10: 46280 | J10: =IF(I10="","",I10-Cover!$C$7) -> 5 | K10: =IF(AND(I10<>"",N(J10)>=0,N(J10)<=14),I10+ROW()/100000,"") -> 46280
A11: Design authority | B11: Approve designs and architecture decisions. | C11: Tech Lead | D11: Product Owner, UX Designer, InfoSec Lead, Dispute Ops Lead | E11: Fortnightly | F11: Tuesday 16:00 | G11: Figma designs, solution design changes | H11: Design sign-off (I-03); architecture decisions | I11: 46280 | J11: =IF(I11="","",I11-Cover!$C$7) -> 5 | K11: =IF(AND(I11<>"",N(J11)>=0,N(J11)<=14),I11+ROW()/100000,"") -> 46280
A12: Compliance and security checkpoint | B12: Track controls, evidence and security testing. | C12: Compliance Lead | D12: InfoSec Lead, Legal Counsel, Product Owner, QA Lead | E12: Fortnightly | F12: Wednesday 15:00 | G12: RTM control view, test results, pen test plan | H12: Evidence gaps closed; compliance risks escalated | I12: 46281 | J12: =IF(I12="","",I12-Cover!$C$7) -> 6 | K12: =IF(AND(I12<>"",N(J12)>=0,N(J12)<=14),I12+ROW()/100000,"") -> 46281
A13: Outcome definitions decision meeting | B13: Decide how dispute outcomes and win rate are defined (CR-05). | C13: Business Sponsor | D13: Finance Lead, Dispute Ops Lead, Product Owner | E13: One-off | F13: Thursday 10:00 | G13: KPI outcome definitions worked example, CR-05 | H13: CR-05 decision; KPI-01 and KPI-02 status updated | I13: 46282 | J13: =IF(I13="","",I13-Cover!$C$7) -> 7 | K13: =IF(AND(I13<>"",N(J13)>=0,N(J13)<=14),I13+ROW()/100000,"") -> 46282
A14: Data governance forum | B14: Approve data use, analytics tracking and data quality rules. | C14: Data Governance Lead | D14: Product Owner, Data Engineering Lead, Compliance Lead | E14: Monthly | F14: First Thursday 13:00 | G14: Tracking plan, data dictionary | H14: Tracking plan approval (I-06) | I14: 46296 | J14: =IF(I14="","",I14-Cover!$C$7) -> 21 | K14: =IF(AND(I14<>"",N(J14)>=0,N(J14)<=14),I14+ROW()/100000,"")
A15: Processor vendor sync | B15: Resolve sandbox issues and track production access. | C15: Project Manager | D15: Processor account manager, Tech Lead | E15: Weekly | F15: Tuesday 17:00 | G15: Vendor action log, defects | H15: Vendor actions and dates; escalation if dates slip | I15: 46280 | J15: =IF(I15="","",I15-Cover!$C$7) -> 5 | K15: =IF(AND(I15<>"",N(J15)>=0,N(J15)<=14),I15+ROW()/100000,"") -> 46280
A16: Ops and servicing readiness huddle | B16: Prepare dispute ops and servicing for launch. | C16: Dispute Ops Lead | D16: Servicing Lead, Product Owner, trainers | E16: Weekly from November | F16: Monday 15:00 | G16: Launch readiness checklist | H16: Training and process readiness actions | I16: 46328 | J16: =IF(I16="","",I16-Cover!$C$7) -> 53 | K16: =IF(AND(I16<>"",N(J16)>=0,N(J16)<=14),I16+ROW()/100000,"")
A17: Pilot merchant feedback call | B17: Hear pilot merchant experience and track exit gates. | C17: Merchant Relationship Lead | D17: Pilot merchants, Product Owner | E17: Weekly during pilot | F17: Friday 11:00 | G17: Pilot KPIs, feedback log | H17: Backlog changes; pilot issues escalated | I17: 46402 | J17: =IF(I17="","",I17-Cover!$C$7) -> 127 | K17: =IF(AND(I17<>"",N(J17)>=0,N(J17)<=14),I17+ROW()/100000,"")
J18: =IF(I18="","",I18-Cover!$C$7) | K18: =IF(AND(I18<>"",N(J18)>=0,N(J18)<=14),I18+ROW()/100000,"")
J19: =IF(I19="","",I19-Cover!$C$7) | K19: =IF(AND(I19<>"",N(J19)>=0,N(J19)<=14),I19+ROW()/100000,"")
A20: Escalation path | J20: =IF(I20="","",I20-Cover!$C$7) | K20: =IF(AND(I20<>"",N(J20)>=0,N(J20)<=14),I20+ROW()/100000,"")
A21: Level | B21: Escalate to | C21: Trigger | E21: How | G21: Response time | J21: =IF(I21="","",I21-Cover!$C$7) | K21: =IF(AND(I21<>"",N(J21)>=0,N(J21)<=14),I21+ROW()/100000,"")
A22: Level 1 | B22: Workstream owner | C22: Issue can be resolved within the team or sprint | E22: Owner resolves and records in RAID | G22: 2 business days | J22: =IF(I22="","",I22-Cover!$C$7) | K22: =IF(AND(I22<>"",N(J22)>=0,N(J22)<=14),I22+ROW()/100000,"")
A23: Level 2 | B23: Product Owner and Project Manager | C23: Affects a sprint goal, a cross-team dependency or a Low-impact change | E23: Raised at weekly status and RAID / change review | G23: 3 business days | J23: =IF(I23="","",I23-Cover!$C$7) | K23: =IF(AND(I23<>"",N(J23)>=0,N(J23)<=14),I23+ROW()/100000,"")
A24: Level 3 | B24: Business Sponsor | C24: Medium-impact change; dependency slip threatening a milestone; unresolved stakeholder conflict | E24: Raised at sponsor 1:1 with options and a recommendation | G24: 5 business days | J24: =IF(I24="","",I24-Cover!$C$7) | K24: =IF(AND(I24<>"",N(J24)>=0,N(J24)<=14),I24+ROW()/100000,"")
A25: Level 4 | B25: Steering Committee | C25: High-impact change; go-live, budget beyond contingency or compliance at risk | E25: Decision paper at next steering committee, or ad hoc meeting within 48 hours if critical | G25: Next meeting or 48 hours | J25: =IF(I25="","",I25-Cover!$C$7) | K25: =IF(AND(I25<>"",N(J25)>=0,N(J25)<=14),I25+ROW()/100000,"")
J26: =IF(I26="","",I26-Cover!$C$7) | K26: =IF(AND(I26<>"",N(J26)>=0,N(J26)<=14),I26+ROW()/100000,"")
J27: =IF(I27="","",I27-Cover!$C$7) | K27: =IF(AND(I27<>"",N(J27)>=0,N(J27)<=14),I27+ROW()/100000,"")
J28: =IF(I28="","",I28-Cover!$C$7) | K28: =IF(AND(I28<>"",N(J28)>=0,N(J28)<=14),I28+ROW()/100000,"")
J29: =IF(I29="","",I29-Cover!$C$7) | K29: =IF(AND(I29<>"",N(J29)>=0,N(J29)<=14),I29+ROW()/100000,"")
J30: =IF(I30="","",I30-Cover!$C$7) | K30: =IF(AND(I30<>"",N(J30)>=0,N(J30)<=14),I30+ROW()/100000,"")
J31: =IF(I31="","",I31-Cover!$C$7) | K31: =IF(AND(I31<>"",N(J31)>=0,N(J31)<=14),I31+ROW()/100000,"")
J32: =IF(I32="","",I32-Cover!$C$7) | K32: =IF(AND(I32<>"",N(J32)>=0,N(J32)<=14),I32+ROW()/100000,"")
J33: =IF(I33="","",I33-Cover!$C$7) | K33: =IF(AND(I33<>"",N(J33)>=0,N(J33)<=14),I33+ROW()/100000,"")
J34: =IF(I34="","",I34-Cover!$C$7) | K34: =IF(AND(I34<>"",N(J34)>=0,N(J34)<=14),I34+ROW()/100000,"")

Sheet Communication Plan
A1: Communication Plan
A2: Merchant Payment Operations & Dispute Hub · Simulation project
A3: Update Next send date and Status after each communication.
A4: ID | B4: Communication | C4: Audience | D4: Purpose | E4: Owner | F4: Channel | G4: Frequency | H4: Artifact | I4: Next send date | J4: Status | K4: Due in (days)
A5: CM-01 | B5: Weekly status report | C5: Business Sponsor, steering committee delegates, workstream leads | D5: Progress, RAG status, top risks and decisions needed | E5: Project Manager | F5: Email and Confluence | G5: Weekly (Friday) | H5: One-page status report | I5: 46276 | J5: Active | K5: =IF(I5="","",I5-Cover!$C$7) -> 1
A6: CM-02 | B6: Steering committee pack | C6: Steering Committee | D6: Decisions with options, business case view, top RAID items | E6: Product Owner and Project Manager | F6: Pre-read and meeting | G6: Fortnightly | H6: Decision paper and short deck | I6: 46287 | J6: Active | K6: =IF(I6="","",I6-Cover!$C$7) -> 12
A7: CM-03 | B7: Sprint review demo | C7: Business stakeholders, dispute ops, finance | D7: Show working software and collect feedback | E7: Product Owner | F7: Live demo | G7: Every 2 weeks | H7: Demo and review notes | I7: 46276 | J7: Active | K7: =IF(I7="","",I7-Cover!$C$7) -> 1
A8: CM-04 | B8: RAID and change digest | C8: Workstream leads | D8: New or escalated items and pending decisions | E8: Project Manager | F8: Confluence page and Slack | G8: Weekly | H8: RAID and change log extract | I8: 46281 | J8: Active | K8: =IF(I8="","",I8-Cover!$C$7) -> 6
A9: CM-05 | B9: Decision memo: dispute outcome definitions | C9: Finance Lead, Dispute Ops Lead, Business Sponsor | D9: Present CR-05 options and recommendation | E9: Product Owner | F9: Memo and meeting | G9: One-off | H9: Decision memo with worked example | I9: 46280 | J9: In Preparation | K9: =IF(I9="","",I9-Cover!$C$7) -> 5
A10: CM-06 | B10: Compliance and security update | C10: Compliance Lead, InfoSec Lead, Legal Counsel | D10: Control status and evidence gaps | E10: Product Owner | F10: Checkpoint meeting | G10: Fortnightly | H10: RTM control assurance view | I10: 46281 | J10: Active | K10: =IF(I10="","",I10-Cover!$C$7) -> 6
A11: CM-07 | B11: Delivery team updates | C11: Delivery squads | D11: Priorities, blockers and scope changes | E11: Product Owner | F11: Stand-up and Slack | G11: Daily | H11: Sprint board | I11: 46276 | J11: Active | K11: =IF(I11="","",I11-Cover!$C$7) -> 1
A12: CM-08 | B12: Ops and servicing readiness bulletin | C12: Dispute ops analysts, servicing agents | D12: Training dates and process changes | E12: Dispute Ops Lead and Servicing Lead | F12: Email and huddle | G12: Weekly from November | H12: Readiness bulletin | I12: 46328 | J12: Planned | K12: =IF(I12="","",I12-Cover!$C$7) -> 53
A13: CM-09 | B13: Relationship manager briefing | C13: Relationship managers | D13: Pilot plan, messaging and objection handling | E13: Merchant Relationship Lead | F13: Team meeting | G13: Monthly, weekly from November | H13: RM enablement pack | I13: 46296 | J13: Planned | K13: =IF(I13="","",I13-Cover!$C$7) -> 21
A14: CM-10 | B14: Pilot merchant invitation and onboarding | C14: Pilot merchants | D14: Invitation, what to expect and how to start | E14: Merchant Relationship Lead and Marketing Lead | F14: Email and onboarding call | G14: One-off, then weekly during pilot | H14: Invitation and welcome emails; onboarding guide | I14: 46363 | J14: Planned | K14: =IF(I14="","",I14-Cover!$C$7) -> 88
A15: CM-11 | B15: Pilot results report | C15: Business Sponsor, Steering Committee | D15: Exit gate results and Wave 1 recommendation | E15: Product Owner | F15: Report and steering committee | G15: Once at pilot end | H15: Pilot results report | I15: 46457 | J15: Planned | K15: =IF(I15="","",I15-Cover!$C$7) -> 182
A16: CM-12 | B16: Vendor escalation note | C16: Processor account manager | D16: Production access and sandbox defect escalation | E16: Project Manager | F16: Email and vendor call | G16: As needed | H16: Escalation note with dates and impact | I16: 46280 | J16: In Preparation | K16: =IF(I16="","",I16-Cover!$C$7) -> 5
K17: =IF(I17="","",I17-Cover!$C$7)
K18: =IF(I18="","",I18-Cover!$C$7)
K19: =IF(I19="","",I19-Cover!$C$7)
K20: =IF(I20="","",I20-Cover!$C$7)
K21: =IF(I21="","",I21-Cover!$C$7)
K22: =IF(I22="","",I22-Cover!$C$7)
K23: =IF(I23="","",I23-Cover!$C$7)
K24: =IF(I24="","",I24-Cover!$C$7)
K25: =IF(I25="","",I25-Cover!$C$7)
K26: =IF(I26="","",I26-Cover!$C$7)
K27: =IF(I27="","",I27-Cover!$C$7)
K28: =IF(I28="","",I28-Cover!$C$7)
... K54: =IF(I54="","",I54-Cover!$C$7)

Sheet Deliverables
A1: Deliverables & Milestones
A2: Merchant Payment Operations & Dispute Hub · Simulation project
A3: Update Status as deliverables move through review and approval.
A4: ID | B4: Deliverable | C4: Phase | D4: Description | E4: Owner | F4: Approver | G4: Due date | H4: Status | I4: Linked artifact | J4: Overdue? | K4: h_due
A5: DL-01 | B5: Discovery findings and problem statement | C5: Discovery | D5: Merchant and ops pain points, current process, opportunity sizing | E5: Product Owner | F5: Business Sponsor | G5: 46213 | H5: Approved | I5: Discovery pack | J5: =IF(OR(A5="",G5=""),"",IF(AND(G5<Cover!$C$7,H5<>"Approved",H5<>"Live document"),"Overdue","No")) -> No | K5: =IF(AND(G5<>"",H5<>"Approved",H5<>"Live document",G5<=Cover!$C$7+30),G5+ROW()/100000,"")
A6: DL-02 | B6: MVP scope baseline | C6: Discovery | D6: Agreed MVP scope, out-of-scope items and assumptions | E6: Product Owner | F6: Business Sponsor | G6: 46220 | H6: Approved | I6: Product_Backlog workbook | J6: =IF(OR(A6="",G6=""),"",IF(AND(G6<Cover!$C$7,H6<>"Approved",H6<>"Live document"),"Overdue","No")) -> No | K6: =IF(AND(G6<>"",H6<>"Approved",H6<>"Live document",G6<=Cover!$C$7+30),G6+ROW()/100000,"")
A7: DL-03 | B7: Solution design | C7: Mobilization and design | D7: Architecture, integrations, data model and security design | E7: Tech Lead | F7: Design authority | G7: 46248 | H7: Approved | I7: Solution design document | J7: =IF(OR(A7="",G7=""),"",IF(AND(G7<Cover!$C$7,H7<>"Approved",H7<>"Live document"),"Overdue","No")) -> No | K7: =IF(AND(G7<>"",H7<>"Approved",H7<>"Live document",G7<=Cover!$C$7+30),G7+ROW()/100000,"")
A8: DL-04 | B8: RAID log | C8: Mobilization and design | D8: Risks, assumptions, issues and dependencies with owners | E8: Project Manager | F8: Business Sponsor | G8: 46255 | H8: Live document | I8: RAID_Log workbook | J8: =IF(OR(A8="",G8=""),"",IF(AND(G8<Cover!$C$7,H8<>"Approved",H8<>"Live document"),"Overdue","No")) -> No | K8: =IF(AND(G8<>"",H8<>"Approved",H8<>"Live document",G8<=Cover!$C$7+30),G8+ROW()/100000,"")
A9: DL-05 | B9: Change log | C9: Mobilization and design | D9: Change requests, impact assessments and decisions | E9: Project Manager | F9: Business Sponsor | G9: 46255 | H9: Live document | I9: Change_Log workbook | J9: =IF(OR(A9="",G9=""),"",IF(AND(G9<Cover!$C$7,H9<>"Approved",H9<>"Live document"),"Overdue","No")) -> No | K9: =IF(AND(G9<>"",H9<>"Approved",H9<>"Live document",G9<=Cover!$C$7+30),G9+ROW()/100000,"")
A10: DL-06 | B10: Product backlog, epics and sprint plan | C10: Build | D10: Ordered backlog with acceptance criteria and sprint plan | E10: Product Owner | F10: Business Sponsor | G10: 46220 | H10: Live document | I10: Product_Backlog workbook | J10: =IF(OR(A10="",G10=""),"",IF(AND(G10<Cover!$C$7,H10<>"Approved",H10<>"Live document"),"Overdue","No")) -> No | K10: =IF(AND(G10<>"",H10<>"Approved",H10<>"Live document",G10<=Cover!$C$7+30),G10+ROW()/100000,"")
A11: DL-07 | B11: Figma MVP designs | C11: Build | D11: Merchant inbox, dispute detail and evidence upload screens | E11: UX Designer | F11: Design authority | G11: 46280 | H11: In Review | I11: Figma file (I-03) | J11: =IF(OR(A11="",G11=""),"",IF(AND(G11<Cover!$C$7,H11<>"Approved",H11<>"Live document"),"Overdue","No")) -> No | K11: =IF(AND(G11<>"",H11<>"Approved",H11<>"Live document",G11<=Cover!$C$7+30),G11+ROW()/100000,"") -> 46280
A12: DL-08 | B12: Requirements traceability matrix | C12: Build | D12: Requirements traced to stories, tests, defects and controls | E12: Product Owner and QA Lead | F12: Compliance Lead | G12: 46275 | H12: Live document | I12: RTM workbook | J12: =IF(OR(A12="",G12=""),"",IF(AND(G12<Cover!$C$7,H12<>"Approved",H12<>"Live document"),"Overdue","No")) -> No | K12: =IF(AND(G12<>"",H12<>"Approved",H12<>"Live document",G12<=Cover!$C$7+30),G12+ROW()/100000,"")
A13: DL-09 | B13: KPI and metrics definitions | C13: Build | D13: Metric catalog, outcome definitions and data dictionary | E13: Product Owner | F13: Business Sponsor | G13: 46283 | H13: In Review | I13: KPI_Definitions workbook | J13: =IF(OR(A13="",G13=""),"",IF(AND(G13<Cover!$C$7,H13<>"Approved",H13<>"Live document"),"Overdue","No")) -> No | K13: =IF(AND(G13<>"",H13<>"Approved",H13<>"Live document",G13<=Cover!$C$7+30),G13+ROW()/100000,"") -> 46283
A14: DL-10 | B14: Business case and GTM plan | C14: Build | D14: Three-scenario business case, rollout plan and launch readiness | E14: Product Owner | F14: Steering Committee | G14: 46289 | H14: In Review | I14: Business_Case_GTM workbook | J14: =IF(OR(A14="",G14=""),"",IF(AND(G14<Cover!$C$7,H14<>"Approved",H14<>"Live document"),"Overdue","No")) -> No | K14: =IF(AND(G14<>"",H14<>"Approved",H14<>"Live document",G14<=Cover!$C$7+30),G14+ROW()/100000,"") -> 46289
A15: DL-11 | B15: Stakeholder engagement plan | C15: Build | D15: Stakeholder register, RACI, governance and communications | E15: Product Owner and Engagement Lead | F15: Business Sponsor | G15: 46282 | H15: In Review | I15: This workbook | J15: =IF(OR(A15="",G15=""),"",IF(AND(G15<Cover!$C$7,H15<>"Approved",H15<>"Live document"),"Overdue","No")) -> No | K15: =IF(AND(G15<>"",H15<>"Approved",H15<>"Live document",G15<=Cover!$C$7+30),G15+ROW()/100000,"") -> 46282
A16: DL-12 | B16: UAT plan and scripts | C16: Build | D16: UAT scope, entry and exit criteria, scripts and schedule | E16: QA Lead | F16: Business Sponsor | G16: 46325 | H16: Not Started | I16: RTM workbook (UAT test cases) | J16: =IF(OR(A16="",G16=""),"",IF(AND(G16<Cover!$C$7,H16<>"Approved",H16<>"Live document"),"Overdue","No")) -> No | K16: =IF(AND(G16<>"",H16<>"Approved",H16<>"Live document",G16<=Cover!$C$7+30),G16+ROW()/100000,"")
A17: DL-13 | B17: Go-live readiness pack | C17: Launch | D17: Launch readiness evidence for go / no-go | E17: Project Manager | F17: Steering Committee | G17: 46360 | H17: Not Started | I17: Business_Case_GTM workbook (Launch Readiness) | J17: =IF(OR(A17="",G17=""),"",IF(AND(G17<Cover!$C$7,H17<>"Approved",H17<>"Live document"),"Overdue","No")) -> No | K17: =IF(AND(G17<>"",H17<>"Approved",H17<>"Live document",G17<=Cover!$C$7+30),G17+ROW()/100000,"")
A18: DL-14 | B18: Hypercare exit and BAU handover plan | C18: Launch | D18: Support model, runbooks and ownership after hypercare | E18: Project Manager | F18: Dispute Ops Lead | G18: 46409 | H18: Not Started | J18: =IF(OR(A18="",G18=""),"",IF(AND(G18<Cover!$C$7,H18<>"Approved",H18<>"Live document"),"Overdue","No")) -> No | K18: =IF(AND(G18<>"",H18<>"Approved",H18<>"Live document",G18<=Cover!$C$7+30),G18+ROW()/100000,"")
A19: DL-15 | B19: Pilot results report | C19: Pilot | D19: Pilot exit gate results and recommendation | E19: Product Owner | F19: Steering Committee | G19: 46457 | H19: Not Started | I19: KPI_Definitions workbook | J19: =IF(OR(A19="",G19=""),"",IF(AND(G19<Cover!$C$7,H19<>"Approved",H19<>"Live document"),"Overdue","No")) -> No | K19: =IF(AND(G19<>"",H19<>"Approved",H19<>"Live document",G19<=Cover!$C$7+30),G19+ROW()/100000,"")
A20: DL-16 | B20: Wave 1 go / no-go pack | C20: Scale | D20: Readiness and business case refresh for Wave 1 | E20: Product Owner | F20: Steering Committee | G20: 46458 | H20: Not Started | I20: Business_Case_GTM workbook | J20: =IF(OR(A20="",G20=""),"",IF(AND(G20<Cover!$C$7,H20<>"Approved",H20<>"Live document"),"Overdue","No")) -> No | K20: =IF(AND(G20<>"",H20<>"Approved",H20<>"Live document",G20<=Cover!$C$7+30),G20+ROW()/100000,"")
J21: =IF(OR(A21="",G21=""),"",IF(AND(G21<Cover!$C$7,H21<>"Approved",H21<>"Live document"),"Overdue","No")) | K21: =IF(AND(G21<>"",H21<>"Approved",H21<>"Live document",G21<=Cover!$C$7+30),G21+ROW()/100000,"")
J22: =IF(OR(A22="",G22=""),"",IF(AND(G22<Cover!$C$7,H22<>"Approved",H22<>"Live document"),"Overdue","No")) | K22: =IF(AND(G22<>"",H22<>"Approved",H22<>"Live document",G22<=Cover!$C$7+30),G22+ROW()/100000,"")
J23: =IF(OR(A23="",G23=""),"",IF(AND(G23<Cover!$C$7,H23<>"Approved",H23<>"Live document"),"Overdue","No")) | K23: =IF(AND(G23<>"",H23<>"Approved",H23<>"Live document",G23<=Cover!$C$7+30),G23+ROW()/100000,"")
J24: =IF(OR(A24="",G24=""),"",IF(AND(G24<Cover!$C$7,H24<>"Approved",H24<>"Live document"),"Overdue","No")) | K24: =IF(AND(G24<>"",H24<>"Approved",H24<>"Live document",G24<=Cover!$C$7+30),G24+ROW()/100000,"")
J25: =IF(OR(A25="",G25=""),"",IF(AND(G25<Cover!$C$7,H25<>"Approved",H25<>"Live document"),"Overdue","No")) | K25: =IF(AND(G25<>"",H25<>"Approved",H25<>"Live document",G25<=Cover!$C$7+30),G25+ROW()/100000,"")
J26: =IF(OR(A26="",G26=""),"",IF(AND(G26<Cover!$C$7,H26<>"Approved",H26<>"Live document"),"Overdue","No")) | K26: =IF(AND(G26<>"",H26<>"Approved",H26<>"Live document",G26<=Cover!$C$7+30),G26+ROW()/100000,"")
J27: =IF(OR(A27="",G27=""),"",IF(AND(G27<Cover!$C$7,H27<>"Approved",H27<>"Live document"),"Overdue","No")) | K27: =IF(AND(G27<>"",H27<>"Approved",H27<>"Live document",G27<=Cover!$C$7+30),G27+ROW()/100000,"")
J28: =IF(OR(A28="",G28=""),"",IF(AND(G28<Cover!$C$7,H28<>"Approved",H28<>"Live document"),"Overdue","No")) | K28: =IF(AND(G28<>"",H28<>"Approved",H28<>"Live document",G28<=Cover!$C$7+30),G28+ROW()/100000,"")
J29: =IF(OR(A29="",G29=""),"",IF(AND(G29<Cover!$C$7,H29<>"Approved",H29<>"Live document"),"Overdue","No")) | K29: =IF(AND(G29<>"",H29<>"Approved",H29<>"Live document",G29<=Cover!$C$7+30),G29+ROW()/100000,"")
J30: =IF(OR(A30="",G30=""),"",IF(AND(G30<Cover!$C$7,H30<>"Approved",H30<>"Live document"),"Overdue","No")) | K30: =IF(AND(G30<>"",H30<>"Approved",H30<>"Live document",G30<=Cover!$C$7+30),G30+ROW()/100000,"")
J31: =IF(OR(A31="",G31=""),"",IF(AND(G31<Cover!$C$7,H31<>"Approved",H31<>"Live document"),"Overdue","No")) | K31: =IF(AND(G31<>"",H31<>"Approved",H31<>"Live document",G31<=Cover!$C$7+30),G31+ROW()/100000,"")
J32: =IF(OR(A32="",G32=""),"",IF(AND(G32<Cover!$C$7,H32<>"Approved",H32<>"Live document"),"Overdue","No")) | K32: =IF(AND(G32<>"",H32<>"Approved",H32<>"Live document",G32<=Cover!$C$7+30),G32+ROW()/100000,"")
... J54: =IF(OR(A54="",G54=""),"",IF(AND(G54<Cover!$C$7,H54<>"Approved",H54<>"Live document"),"Overdue","No")) | K54: =IF(AND(G54<>"",H54<>"Approved",H54<>"Live document",G54<=Cover!$C$7+30),G54+ROW()/100000,"")
